{
  "assetId": "cmplb8bff000bdgvczc47nulj",
  "name": "[A.25.0038 \"2025년 예비창업패키지\" JN Build-Up Ca] 어려운 점 및 개선",
  "fileName": "A.25.0038_\"2025년 예비창업패키지\" JN Build-Up Camp 기획·운영_결과보고서",
  "mimeType": "application/pdf",
  "sizeMB": 5.2,
  "kind": "pdf",
  "totalPages": 29,
  "pages": [
    {
      "pageNumber": 1,
      "text": "2025 \tJN_Build \tup_Camp \t결과 \t보고서\n2025.07.01. \t~ \t2025.07.31.",
      "firstLine": "2025 \tJN_Build \tup_Camp \t결과 \t보고서"
    },
    {
      "pageNumber": 2,
      "text": "- \t2 \t-\n1. \t개요\n1.1) \t프로그램 \t개요\n❍ \t목적\n- \t지속적인 \t작은 \t실행을 \t통해 \t지속가능한 \t임팩트를 \t만드는 \tAct-preneur \t육성\n- \tBM \t고도화를 \t위한 \tMVP \t및 \t시장성 \t분석 \t계획 \t수립\n❍ \t목표\n- \tMVP \t고도화 \t보고서와 \t시장성 \t분석 \t보고서 \t완성 \t등 \t2개의 \t완성된 \t실행 \t계획서 \t도출을\n통해 \t즉시 \t실행 \t가능한 \t액션 \t플랜 \t확보\n- \t교육 \t이후에도 \t스스로 \t작은 \t실행을 \t계획하고 \t반복할 \t수 \t있는 \t지속적 \t실행 \t역량 \t배양\n- \t생성형 \tAI를 \t활용한 \t효율적인 \t창업 \t프로세스 \t체득을 \t통한 \tAI \t활용 \t창업 \t생산성 \t향상\n- \t실제 \t현장에서 \t적용 \t가능한 \t체계적인 \t고객 \t검증 \t및 \t시장 \t진입 \t전략 \t완성을 \t통해\n실효성 \t있는 \t고객 \t검증 \t방법론 \t습득\n❍ \t대상\n- \t전남창경 \t예비창업패키지 \t합격자 \t27팀\n❍ \t기간\n- \t2025년 \t7월 \t9일(수) \t~ \t10일(목) \t[1박2일]\n- \tDay \t1: \tMVP \t고도화 \t보고서 \t완성 \t(13:00~20:00)\n- \tDay \t2: \t시장성 \t분석 \t보고서 \t완성 \t(09:00~16:00)\n❍ \t방식\n- \t워크숍 \t중심의 \t실습 \t교육 \t진행\n- \t전현직 \t창업 \t전문가들의 \t실시간 \t1:1 \t코칭\n- \t다양한 \t생성형 \tAI \t툴을 \t직접 \t활용하여 \t리서치, \t글쓰기, \t분석을 \t진행하는 \tAI \t활용 \t실습\n- \t작성한 \t내용에 \t대한 \t즉석 \t피드백과 \t개선 \t방향 \t제시\n2. \t프로젝트 \t운영 \t목표 \t및 \t기대효과\n2.1) \t운영 \t목적\n❍ \tAI \t활용, \t전문가 \t멘토링, \t실전 \t중심 \t교육의 \t삼위일체를 \t통한 \t창업 \t성공 \t기반 \t마련\n- \t이론 \t중심의 \t일방향 \t강의를 \t탈피하고, \t참여자가 \t직접 \t템플릿을 \t작성하고 \t실습하는 \t워크숍\n중심 \t교육\n- \t실제 \t창업 \t경험이 \t있는 \t전문가들이 \t개별 \t맞춤형 \t코칭 \t제공\n- \t현장에서 \t바로 \t적용 \t가능한 \t구체적이고 \t실행 \t가능한 \t계획 \t수립에 \t집중\n- \tChatGPT, \tClaude, \tPerplexity \t등 \t다양한 \tAI \t툴을 \t활용하여 \t창업 \t과정의 \t효율성 \t극대",
      "firstLine": "- \t2 \t-"
    },
    {
      "pageNumber": 3,
      "text": "- \t3 \t-\n화\n<ai \t협업 \t가이드> \t<올바른 \tai \t사용법>\n❍ \t지속적인 \t작은 \t실행을 \t통해 \t지속가능한 \t임팩트를 \t만드는 \tAct-preneur \t육성\n- \t큰 \t변화보다는 \t작은 \t실행들의 \t연쇄를 \t통해 \t지속가능한 \t임팩트를 \t만들어내는 \t창업가 \t양성\n- \t교육 \t이후 \t스스로 \t작은 \t실행을 \t계획하고 \t반복할 \t수 \t있는 \t자립적 \t실행력 \t배양\n- \t실현 \t가능한 \t작은 \t계획을 \t설계하고 \t지속적으로 \t실행하는 \t역량 \t개발\n❍ \tBM \t고도화를 \t위한 \tMVP \t및 \t시장성 \t분석 \t계획 \t수립\n- \t최소기능제품(MVP)을 \t체계적으로 \t고도화하여 \t실제 \t시장에서 \t검증 \t가능한 \t구체적인 \t솔루\n션과 \t실행 \t계획 \t완성\n- \tPEST, \tSTP, \t4P, \tAARRR \t등 \t체계적인 \t시장 \t분석을 \t통해 \t비즈니스 \t모델의 \t확장 \t가능성\n과 \t실질적인 \t시장진입전략 \t도출\n- \tMVP와 \t시장성 \t분석 \t결과를 \t종합하여 \t지속가능하고 \t확장 \t가능한 \t비즈니스 \t모델과 \t사업\n계획서 \t고도화의 \t견고한 \t기반 \t구축\n<실행력 \t기반 \t액트프러너 \t육성> \t<연쇄 \t실행을 \t통한 \t임팩트 \t창출>",
      "firstLine": "- \t3 \t-"
    },
    {
      "pageNumber": 4,
      "text": "- \t4 \t-\n<바로 \t실행 \t가능한 \tMVP \t고도화> \t<지속가능한 \t성장을 \t위한 \t시장성 \t분석>\n2.2) \t기대 \t효과\n❍ \tMVP \t고도화 \t및 \t실행 \t계획 \t수립 \t(Output \t& \tOutcome)\n- \tOutput: \t참가자들은 \tMVP \t고도화를 \t통해 \t문제, \t고객, \t핵심가치, \t솔루션을 \t명확히 \t정의하\n고, \t검증 \t가능한 \tMVP \t계획(가설, \tKPI, \t실행 \t계획)을 \t구체화함\n- \tOutcome: \t참가자들은 \t최소한의 \t자원으로 \t아이디어의 \t시장성을 \t빠르게 \t검증하고 \t개선\n방향을 \t도출할 \t수 \t있는 \t실질적인 \tMVP \t실행 \t역량을 \t확보함\n❍ \t시장성 \t분석 \t및 \t성장 \t전략 \t수립 \t(Output \t& \tOutcome)\n- \tOutput: \t참가자들은 \tPEST, \tTAM-SAM-SOM, \tSTP \t분석을 \t통해 \t시장 \t기회를 \t파악하\n고, \t4P, \tAIDA, \tAARRR \t프레임워크를 \t활용하여 \t고객 \t획득부터 \t성장까지의 \t전략적 \t로드\n맵을 \t완성함\n- \tOutcome: \t참가자들은 \t데이터 \t기반의 \t체계적인 \t시장 \t분석을 \t통해 \t비즈니스 \t모델의 \t확장\n가능성과 \t실질적인 \t시장 \t진입 \t전략을 \t수립하고, \t지속가능한 \t성장 \t기반을 \t마련함\n❍ \tAI \t활용 \t및 \tAct-preneur \t역량 \t강화 \t(Output \t& \tOutcome)\n- \tOutput: \t참가자들은 \tChatGPT, \tClaude, \tPerplexity \t등 \t다양한 \t생성형 \tAI \t툴을 \t활용하\n여 \t리서치, \t글쓰기, \t분석을 \t진행하고, \t창업에 \t특화된 \tAI \t활용법을 \t실습함\n- \tOutcome: \t참가자들은 \tAI를 \t단순 \t도구가 \t아닌 \t창업가의 \t사고력을 \t확장하는 \t파트너로 \t활\n용하는 \t올바른 \tAI \t활용법을 \t체득하며, \t교육 \t이후에도 \t스스로 \t작은 \t실행을 \t계획하고 \t반복\n할 \t수 \t있는 \t자립적 \tAct-preneur \t역량을 \t배양함\n3. \t프로그램 \t세부 \t일정",
      "firstLine": "- \t4 \t-"
    },
    {
      "pageNumber": 5,
      "text": "- \t5 \t-\n3.1) \t교육 \t커리큘럼\n❍ \tDay \t1: \tMVP \t고도화 \t보고서 \t완성\n- \t솔루션 \t고도화: \t문제-고객-핵심가치-솔루션 \t정의\n- \tMVP \t계획 \t수립: \t가설, \tKPI, \t실행 \t계획\n- \t1:1 \t코칭: \t개별 \t맞춤형 \t피드백\n❍ \tDay \t2: \t시장성 \t분석 \t보고서 \t완성\n- \t시장 \t분석: \tPEST/TSS, \tSTP \t전략\n- \t고객 \t전략: \t벤치마킹, \t4P, \tAIDA \t분석\n- \t성장 \t전략: \tAARRR \t프레임워크 \t적용\n3.2) \t프로그램 \t세부 \t타임테이블\n❍ \t1일차 \t(13:00~20:10)\n진행 \t시간 \t프로그램 \t내용 \t운영방식\n13:00~13:10 \tOT \t사전준비 \t/ \t프로그램 \t목적 \t및 \t내용 \t소개 \t-\n13:10~14:10 \t1교시: \t문제 \t명확화 \t문제 \t원인 \t분석을 \t통한 \t문제 \t정의 \t강의, \t워크숍\n14:10~15:10 \t2교시: \t고객 \t명확화 \t페르소나 \t분석을 \t통한 \t고객 \t구체화 \t강의, \t워크숍\n15:10~16:10 \t3교시: \t핵심가치 \t명확화 \t기존 \t솔루션 \t분석을 \t통한 \t핵심가치 \t도출 \t강의, \t워크숍\n16:10~17:10 \t4교시: \t솔루션 \t명확화 \t창업가 \t관점 \t도출을 \t통한 \t솔루션 \t정의 \t강의, \t워크숍\n17:10~18:10 \t석식\n18:10~19:10 \t5교시: \tMVP \t계획 \t수립 \tMVP \t계획 \t수립 \t방법론 \t강의, \t워크숍\n19:10~20:10 \t6교시: \t최종 \t정리 \t및 \t제출 \tMVP \t고도화 \t보고서 \t완성 \t워크숍, \t코칭\n*상황에 \t따라 \t변경될 \t수 \t있음\n❍ \t2일차 \t(09:00~16:00)\n진행 \t시간 \t프로그램 \t내용 \t운영방식\n09:00~09:10 \tOT \t2일차 \t교육 \t안내 \t-\n09:10~10:00 \t1교시: \tPEST/TSS \t거시환경 \t분석 \t및 \t시장 \t규모 \t설정 \t강의, \t워크숍\n10:00~11:00 \t2교시: \tSTP \t시장 \t세분화 \t및 \t타겟팅 \t전략 \t강의, \t워크숍\n11:00~12:00 \t3교시: \t벤치마킹/4P \t경쟁사 \t분석 \t및 \t마케팅 \t믹스 \t전략 \t강의, \t워크숍\n12:00~13:00 \t점심 \t식사\n13:00~14:00 \t4교시: \tAIDA \t고객 \t구매 \t여정 \t분석 \t강의, \t워크숍\n14:00~15:00 \t5교시: \tAARRR \t성장 \t해킹 \t프레임워크 \t적용 \t강의, \t워크숍\n15:00~16:00 \t6교시: \t최종 \t정리 \t및 \t제출 \t시장성 \t분석 \t보고서 \t완성 \t워크숍, \t코칭\n*상황에 \t따라 \t변경될 \t수 \t있음",
      "firstLine": "- \t5 \t-"
    },
    {
      "pageNumber": 6,
      "text": "- \t6 \t-",
      "firstLine": "- \t6 \t-"
    },
    {
      "pageNumber": 7,
      "text": "- \t7 \t-\n❍ \t투입인력\n성명 \t주요 \t이력\n임재성\n§ \t현) \t언더독스(주) \t코치\n§ \t전) \t알에스 \t건재 \t대표\n§ \t전) \t㈜모믹스 \t기술 \t영업 \t이사\n§ \t관련 \t프로젝트 \t경험: \t연대 \t아이디어톤, \t창업씨앗공방 \t등\n유승준\nŸ \t현) \t언더독스코치\nŸ \t전) \t㈜스마트스코어 \t전략기획실 \t근무\nŸ \t전) \t(주)바로솔루션대표 \t- \t댕집사\nŸ \t전) \t(주)터치앤뷰티대표- \tBELO\n김경희\nŸ \t현) \t(주)비파밍 \t대표\nŸ \t전) \t로컬상권 \t멘토링(세종, \t화순 \t등)\nŸ \t전) \t울산 \t콘텐츠 \t코리아랩 \t멘토\n하지수 Ÿ \t현) \t㈜여수와 \t대표\nŸ \t전) \t중기부 \t로컬크리에이터 \t등 \t심사위원\n윤은영 § \t현) \t웰링 \t대표\n§ \t전) \t하나금융그룹 \t등 \t소셜벤처 \t심사위원",
      "firstLine": "- \t7 \t-"
    },
    {
      "pageNumber": 8,
      "text": "- \t8 \t-\n3.2) \t프로그램 \t세부 \t교육안\n❍ \t강의 \t목표 \t및 \t세부 \t교육 \t내용\n프로그램 \tSTEP \t1: \t문제의 \t본질 \t분석을 \t통한 \t문제 \t명확화\n강의 \t목표 \t문제의 \t근본 \t원인을 \t분석하여 \t해결 \t가능한 \t핵심 \t문제를 \t정의하고 \t창업가만의 \t관점을 \t도출\n세부 \t내용\n- \t문제의 \t본질 \t파악 \t및 \t대상 \t범위 \t설정을 \t통해 \t해결하려는 \t문제를 \t명확히 \t정의\n- \t문제의 \t크기 \t측정 \t및 \t심각성, \t시급성 \t분석을 \t통해 \t객관적인 \t문제 \t규모 \t파악\n- \t근본 \t원인 \t분석(5 \tWhy \t기법)을 \t통해 \t표면적 \t문제가 \t아닌 \t진짜 \t해결해야 \t할 \t원인 \t도출\n템플릿\n및 \t툴킷\n진행 \t방식 \t강의 \t및 \t워크숍\n기대 \t효과 \t- \t창업가가 \t해결하고자 \t하는 \t문제의 \t본질을 \t정확히 \t파악하여 \t효과적인 \t솔루션 \t설계의 \t기반 \t마련\n프로그램 \tSTEP \t2: \t구체적 \t페르소나 \t분석을 \t통한 \t타겟 \t고객 \t명확화\n미션 \t목표 \t문제를 \t가장 \t크게 \t느끼는 \t구체적인 \t페르소나를 \t정의하고 \t고객의 \t니즈와 \t지불의향을 \t분석\n세부 \t내용\n- \t고객 \t구체화(인구통계학적 \t특성)를 \t통해 \t직접 \t만나 \t인터뷰 \t가능한 \t단 \t한 \t사람까지 \t구체화\n- \t타겟 \t고객 \t규모 \t산정 \t및 \t고객의 \t불편함 \t분석(외적/내적/철학적 \t니즈)을 \t통한 \t깊은 \t고객 \t이해\n- \t지불의향 \t분석 \t및 \t현재 \t대안에 \t지불하는 \t비용 \t조사를 \t통해 \t실제 \t비즈니스 \t가능성 \t검증\n템플릿\n및 \t툴킷\n진행 \t방식 \t강의 \t및 \t워크숍\n기대 \t효과 - \t창업가가 \t명확한 \t타겟 \t고객을 \t설정하여 \t고객 \t중심의 \t솔루션 \t개발과 \t효과적인 \t마케팅 \t전략 \t수\n립이 \t가능",
      "firstLine": "- \t8 \t-"
    },
    {
      "pageNumber": 9,
      "text": "- \t9 \t-\n프로그램 \tSTEP \t3: \t기존 \t솔루션 \t분석을 \t통한 \t차별화 \t핵심가치 \t도출\n강의 \t목표 \t기존 \t솔루션들의 \t만족/불만족 \t요소를 \t분석하여 \t고객이 \t진정 \t원하는 \t차별화된 \t핵심가치를 \t발굴\n세부 \t내용\n- \t기존 \t솔루션 \t분석을 \t통해 \t페르소나가 \t현재 \t사용하는 \t모든 \t대안들의 \t장단점 \t파악\n- \t만족 \t요소 \t분석 \t및 \t불만족 \t이유 \t파악을 \t통해 \t기존 \t솔루션이 \t해결하지 \t못하는 \t지점 \t발견\n- \t차별화 \t요소 \t정의 \t및 \t해결되지 \t않은 \t원인 \t분석을 \t통해 \t우리만의 \t독특한 \t가치 \t제안 \t도출\n템플릿\n및 \t툴킷\n진행 \t방식 \t강의 \t및 \t워크숍\n기대 \t효과 - \t기존 \t경쟁사와 \t명확히 \t차별화되는 \t핵심가치를 \t찾아 \t고객에게 \t독특한 \t가치를 \t제공할 \t수 \t있는\n경쟁우위를 \t확보\n프로그램 \tSTEP \t4: \t핵심가치 \t기반 \t솔루션 \t구체화 \t및 \t시각화\n강의 \t목표 \t도출된 \t핵심가치를 \t담아 \t고객이 \t쉽게 \t이해하고 \t공감할 \t수 \t있도록 \t솔루션을 \t구체화하고 \t시각화\n세부 \t내용\n- \t문제 \t해결 \t방법론 \t구체화를 \t통해 \t핵심가치를 \t실제 \t솔루션으로 \t구현하는 \t방법 \t설계\n- \t완전한 \t문제 \t해결 \t여부 \t검증 \t및 \t차별화 \t요소 \t강화를 \t통한 \t솔루션의 \t완성도 \t제고\n- \t예상 \t수익 \t산출 \t및 \t반복 \t구매 \t가능성 \t분석을 \t통한 \t지속가능한 \t비즈니스 \t모델 \t기초 \t설계\n템플릿\n및 \t툴킷\n진행 \t방식 \t강의 \t및 \t워크숍\n기대 \t효과 - \t추상적인 \t아이디어를 \t구체적이고 \t실행 \t가능한 \t솔루션으로 \t발전시켜 \t고객과 \t투자자에게 \t명확히\n전달",
      "firstLine": "- \t9 \t-"
    },
    {
      "pageNumber": 10,
      "text": "- \t10 \t-\n프로그램 \tSTEP \t5: \t검증 \t가능한 \tMVP \t계획 \t수립\n강의 \t목표 \t최소한의 \t자원으로 \t핵심가치를 \t검증할 \t수 \t있는 \t구체적이고 \t실행 \t가능한 \tMVP \t계획을 \t수립\n세부 \t내용\n- \t검증 \t가설 \t설정 \t및 \tKPI \t정의를 \t통해 \t측정 \t가능한 \t성과 \t지표와 \t목표치 \t설정\n- \t핵심 \t질문 \t정의 \t및 \t가설 \t검증 \t방법 \t구체화를 \t통한 \t체계적인 \t실험 \t설계\n- \t실행 \t계획 \t수립 \t및 \t자원/예산 \t계획을 \t통해 \t2주 \t내 \t실행 \t가능한 \t구체적 \t액션 \t플랜 \t완성\n템플릿\n및 \t툴킷\n진행 \t방식 \t강의 \t및 \t워크숍\n기대 \t효과 - \t체계적인 \tMVP \t실험을 \t통해 \t최소 \t비용으로 \t아이디어의 \t시장성을 \t빠르게 \t검증하고 \t개선 \t방향\n을 \t도출\n프로그램 \tSTEP \t6: \t거시적 \t시장성 \t분석을 \t통한 \t진입 \t전략 \t수립\n강의 \t목표 PEST, \tTAM-SAM-SOM, \tSTP \t분석을 \t통해 \t시장 \t기회를 \t파악하고 \t체계적인 \t시장 \t진입 \t전략을\n수립\n세부 \t내용\n- \tPEST \t분석을 \t통한 \t거시환경(정치적, \t경제적, \t사회적, \t기술적) \t요인 \t분석 \t및 \t기회/위협 \t요소 \t도출\n- \tTAM-SAM-SOM \t분석을 \t통한 \t단계별 \t목표 \t시장 \t규모 \t설정 \t및 \t현실적인 \t시장 \t진입 \t계획 \t수립\n- \tSTP \t전략(시장 \t세분화, \t타겟팅, \t포지셔닝)을 \t통한 \t구체적인 \t시장 \t접근 \t방법 \t및 \t차별화 \t전략 \t완\n성\n템플릿\n및 \t툴킷\n진행 \t방식 \t강의 \t및 \t워크숍\n기대 \t효과 - \t데이터 \t기반의 \t체계적인 \t시장 \t분석을 \t통해 \t리스크를 \t최소화하고 \t성공 \t가능성이 \t높은 \t시장 \t진\n입 \t전략을 \t확보",
      "firstLine": "- \t10 \t-"
    },
    {
      "pageNumber": 11,
      "text": "- \t11 \t-\n프로그램 \tSTEP \t7: \t고객 \t여정 \t기반 \t성장 \t전략 \t설계\n강의 \t목표 \t4P, \tAIDA, \tAARRR \t프레임워크를 \t활용하여 \t고객 \t획득부터 \t성장까지의 \t전략적 \t로드맵을 \t완성\n세부 \t내용\n- \t4P \t전략(제품, \t가격, \t유통, \t촉진)을 \t통한 \t종합적인 \t마케팅 \t믹스 \t전략 \t수립\n- \tAIDA \t분석(주의-관심-욕구-행동)을 \t통한 \t고객 \t구매 \t심리 \t여정 \t분석 \t및 \t단계별 \t전환 \t전략 \t설계\n- \tAARRR \t프레임워크(획득-활성화-유지-수익-추천)를 \t통한 \t지속가능한 \t성장 \t엔진 \t구축 \t계획 \t완성\n템플릿\n및 \t툴킷\n진행 \t방식 \t강의 \t및 \t워크숍\n기대 \t효과 - \t고객의 \t전체 \t여정을 \t고려한 \t통합적인 \t성장 \t전략을 \t통해 \t지속가능하고 \t확장 \t가능한 \t비즈니스\n성장 \t기반을 \t마련",
      "firstLine": "- \t11 \t-"
    },
    {
      "pageNumber": 12,
      "text": "- \t12 \t-\n4. \t참여자 \t결과 \t보고서 \t(MVP, \t시장성)\n4.1) \t참여자 \t결과 \t보고서 \t세부 \t내용\nNo. \t대표자명 \tMVP \t검증 \t보고서 \t시장성 \t분석 \t보고서\n1 \t강우리\n2 \t김대운",
      "firstLine": "- \t12 \t-"
    },
    {
      "pageNumber": 13,
      "text": "- \t13 \t-\nNo. \t대표자명 \tMVP \t검증 \t보고서 \t시장성 \t분석 \t보고서\n3 \t백유빈\n4 \t최창현",
      "firstLine": "- \t13 \t-"
    },
    {
      "pageNumber": 14,
      "text": "- \t14 \t-\nNo. \t대표자명 \tMVP \t검증 \t보고서 \t시장성 \t분석 \t보고서\n5 \t홍지원\n6 장예서\n(원용준)",
      "firstLine": "- \t14 \t-"
    },
    {
      "pageNumber": 15,
      "text": "- \t15 \t-\nNo. \t대표자명 \tMVP \t검증 \t보고서 \t시장성 \t분석 \t보고서\n7 \t정재정\n8 \t최윤호",
      "firstLine": "- \t15 \t-"
    },
    {
      "pageNumber": 16,
      "text": "- \t16 \t-\nNo. \t대표자명 \tMVP \t검증 \t보고서 \t시장성 \t분석 \t보고서\n9 \t이지현\n10 \t박경옥",
      "firstLine": "- \t16 \t-"
    },
    {
      "pageNumber": 17,
      "text": "- \t17 \t-\nNo. \t대표자명 \tMVP \t검증 \t보고서 \t시장성 \t분석 \t보고서\n11 \t양준길\n12 \t이윤정",
      "firstLine": "- \t17 \t-"
    },
    {
      "pageNumber": 18,
      "text": "- \t18 \t-\nNo. \t대표자명 \tMVP \t검증 \t보고서 \t시장성 \t분석 \t보고서\n13 \t임한규\n14 \t이상준",
      "firstLine": "- \t18 \t-"
    },
    {
      "pageNumber": 19,
      "text": "- \t19 \t-\nNo. \t대표자명 \tMVP \t검증 \t보고서 \t시장성 \t분석 \t보고서\n15 \t김미경\n16 \t서은경",
      "firstLine": "- \t19 \t-"
    },
    {
      "pageNumber": 20,
      "text": "- \t20 \t-\nNo. \t대표자명 \tMVP \t검증 \t보고서 \t시장성 \t분석 \t보고서\n17 \t임성진\n18 \t김채림",
      "firstLine": "- \t20 \t-"
    },
    {
      "pageNumber": 21,
      "text": "- \t21 \t-\nNo. \t대표자명 \tMVP \t검증 \t보고서 \t시장성 \t분석 \t보고서\n19 \t김현빈\n20 \t이익주",
      "firstLine": "- \t21 \t-"
    },
    {
      "pageNumber": 22,
      "text": "- \t22 \t-\nNo. \t대표자명 \tMVP \t검증 \t보고서 \t시장성 \t분석 \t보고서\n21 \t김완기\n22 \t김억",
      "firstLine": "- \t22 \t-"
    },
    {
      "pageNumber": 23,
      "text": "- \t23 \t-\nNo. \t대표자명 \tMVP \t검증 \t보고서 \t시장성 \t분석 \t보고서\n23 \t유성규\n24 \t이창민",
      "firstLine": "- \t23 \t-"
    },
    {
      "pageNumber": 24,
      "text": "- \t24 \t-\nNo. \t대표자명 \tMVP \t검증 \t보고서 \t시장성 \t분석 \t보고서\n25 \t정연수",
      "firstLine": "- \t24 \t-"
    },
    {
      "pageNumber": 25,
      "text": "- \t25 \t-\n5. \t참가자 \t만족도 \t조사 \t및 \t피드백\n5.1) \t참가자 \t만족도\n❍ \t만족도 \t조사 \t결과(종합)\n프로그램 \t전체 \t만족도 \t프로그래머 \t추천 \t의사\n95.6% \t[3점 \t이상] \t91.2% \t만족[5점 \t이상]\n창업에 \t대한 \t이해도 \t창업 \t방법론 \t학습도\n95.7% \t만족[3점 \t이상] \t95.7% \t만족[3점 \t이상]\n강의/워크숍 \t참여 \t형태 \t및 \t구성 \t가설 \t설정의 \t이해도\n100% \t만족[3점 \t이상] \t95.7% \t만족[3점 \t이상]\nBM \t고도화 \t및 \t구체화 \t코치의 \t교육 \t이해도\n100% \t만족[3점 \t이상] \t100% \t만족[3점 \t이상]",
      "firstLine": "- \t25 \t-"
    },
    {
      "pageNumber": 26,
      "text": "- \t26 \t-\n코치의 \t열정 \t코칭의 \t적절성\n100% \t만족[3점 \t이상] \t100% \t만족[3점 \t이상]\n사업의 \t실질적인 \t도움 \t1:1 \t코칭의 \t만족도\n100% \t만족[3점 \t이상] \t100% \t만족[4점 \t이상]\n운영진의 \t몰입 \t환경 \t조성 \t교육 \t운영 \t관련 \t커뮤니케이션 \t원활성\n100% \t만족[3점 \t이상] \t100% \t만족[4점 \t이상]",
      "firstLine": "- \t26 \t-"
    },
    {
      "pageNumber": 27,
      "text": "- \t27 \t-\n5.2) \t참가자 \t만족도 \t데이터 \t분석\n❍ \t개요 \t본 \t보고서는 \t<Jn-Build \tup \tCamp> \t교육 \t프로그램의 \t만족도 \t결과를 \t분석하여 \t핵심\n강점과 \t개선 \t필요 \t사항을 \t도출하고, \t향후 \t프로그램 \t기획에 \t활용될 \t시사점을 \t제시하고자 \t함\n❍ \t종합 \t결론 \t<Jn-Build \tup \tCamp>는 \t참가자들에게 \t매우 \t긍정적인 \t경험을 \t제공했으며,\n특히 \t실질적인 \t사업 \t구체화와 \t역량 \t강화에 \t크게 \t기여한 \t프로그램으로 \t평가. \t핵심 \t강점은\n탁월한 \t코칭 \t역량, \t실질적인 \t커리큘럼, \t그리고 \t실제 \t사업 \t적용 \t가능성. \t그러나 \t촉박한\n일정과 \t보고서 \t작성 \t부담은 \t학습 \t효과를 \t저해하는 \t주요 \t개선 \t과제로 \t나타남.\n❍ \t주요 \t분석 \t결과\n￿ \t프로그램 \t참여 \t동기 \t및 \t핵심 \t목표 \t달성\n• \t주요 \t참여 \t동기: \t사업 \t구체화, \t사업계획서 \t고도화, \t대표 \t역량 \t강화, \tMVP \t고도화, \t시장\n타당성 \t및 \t고객 \t문제 \t점검 \t등.\n• \t목표 \t달성 \t기여:\n◦ \t사업 \t빌드업과 \tNext \tLevel \tUp을 \t위한 \t사업계획서 \t퀄리티 \t향상에 \t도움이\n되었다는 \t평가.\n◦ \t사업을 \t전략적으로 \t진행할 \t수 \t있을 \t것 \t같다는 \t기대감 \t형성.\n◦ \t실현 \t가능한 \tMVP \t전략 \t고도화에 \t기여.\n￿ \t가장 \t만족스러웠던 \t점 \t(강점)\n• \t전문적이고 \t열정적인 \t코칭 \t및 \t멘토링:\n◦ \t코치님들의 \t자세하고 \t열정적인 \t코칭이 \t가장 \t만족스러운 \t요소로 \t꼽힘.\n◦ \t밀도 \t있는 \t피드백과 \t실시간 \t코칭 \t제공.\n◦ \t개인적인 \t경험 \t및 \t창업 \t팁 \t공유, \t선배 \t창업가의 \t현실적인 \t조언이 \t큰 \t도움.\n◦ \t조별 \t코치 \t배정을 \t통해 \t노하우 \t전수 \t및 \t아이디어 \t개선 \t방법 \t논의 \t가능.\n◦ \t비현실적인 \t일정 \t속에서도 \t피교육자가 \t하나라도 \t배울 \t수 \t있도록 \t상세히 \t봐주심.\n• \t실질적이고 \t체계적인 \t커리큘럼:\n◦ \tMVP \t계획 \t수립, \t시장성 \t분석, \t비즈니스 \t구체화가 \t가장 \t만족도 \t높은 \t교육 \t콘텐츠.\n◦ \t실무 \t적용에 \t매우 \t유용하며 \t실질적인 \t성장 \t전략으로 \t연결 \t가능.\n◦ \t문제 \t정의, \t시장 \t타겟팅, \tAARRR \t전략 \t등 \t창업 \t초기 \t단계에 \t필요한 \t실전\n프레임워크를 \t체계적으로 \t습득.\n◦ \tAI \t사용법 \t학습 \t및 \t챗 \tGPT \t활용 \t연계법 \t또한 \t만족도 \t높음.\n• \t실습 \t중심 \t및 \t적용 \t가능성:\n◦ \t알찬 \t강의와 \t실습, \t실습해볼 \t수 \t있는 \t것이 \t좋았다는 \t의견 \t다수.",
      "firstLine": "- \t27 \t-"
    },
    {
      "pageNumber": 28,
      "text": "- \t28 \t-\n◦ \t실제 \t적용 \t가능성이 \t만족도에 \t큰 \t영향.\n◦ \t타 \t프로그램과 \t비교하여 \t실습 \t중심이라는 \t점이 \t차별점으로 \t언급.\n• \t네트워킹 \t기회:\n◦ \t효율적 \t창업 \t네트워킹이 \t참여 \t동기 \t중 \t하나.\n◦ \t네트워킹 \t과정을 \t통한 \t지식 \t습득 \t및 \t비슷한 \t분야 \t창업자들과의 \t팁 \t공유 \t시간 \t유용.\n• \t운영진의 \t노력 \t및 \t환경:\n◦ \t친절하고 \t적극적인 \t관계자들.\n◦ \t진행자님의 \t능숙한 \t진행.\n◦ \t전남창조경제혁신센터 \t관계자, \t강사, \t멘토들의 \t열정적이고 \t프로페셔널한 \t태도에\n대한 \t감사.\n◦ \t편안한 \t공간 \t제공과 \t오션뷰의 \t멋진 \t장소도 \t긍정적 \t요소.\n￿ \t가장 \t아쉬웠던 \t점 \t(개선 \t필요 \t영역)\n• \t시간 \t부족 \t및 \t촉박한 \t일정:\n◦ \t\"내용에 \t비해 \t너무 \t짧은 \t강의 \t시간\", \t\"짧은 \t일정으로 \t소화하기 \t힘듦\", \t\"보고서를\n동시에 \t작성하여야 \t해서 \t배울 \t수 \t없음\" \t등 \t시간 \t부족에 \t대한 \t불만 \t가장 \t많음.\n◦ \t일부 \t참가자는 \t프로그램의 \t계획 \t자체가 \t\"매우 \t무리수\"이며, \t\"머릿속으로 \t익힐\n시간이 \t없이 \t보고서를 \t작성하니 \t하나도 \t안 \t남는다\"고 \t지적.\n◦ \t1:1 \t코칭 \t또한 \t\"보고서 \t작성 \t시간에 \t코칭 \t시간을 \t고려하지 \t않고 \t진행되어 \t뭔가\n급하게 \t진행되는 \t느낌\"을 \t받았다고 \t함.\n• \t보고서 \t작성 \t부담:\n◦ \t강의와 \t동시 \t진행되는 \t보고서 \t작성이 \t학습 \t집중도를 \t저해.\n◦ \t\"진행 \t시간 \t대비 \t보고서 \t질문 \t항목 \t많음\" \t지적.\n• \tAI \t교육의 \t깊이:\n◦ \tAI \t교육에 \t대한 \t추가 \t요구.\n◦ \t\"툴 \t사용 \t시연이 \t있었다면\" \t더 \t좋았을 \t것이라는 \t의견.\n• \t교육 \t장소/환경 \t관련:\n◦ \t\"교육 \t장소가 \t좀만 \t더 \t컸으면 \t자리가 \t좁았어요\".\n￿ \t추가적으로 \t필요한 \t교육 \t및 \t지원 \t사항\n• \t투자 \t및 \t자금 \t교육: \t투자 \t및 \t자금 \t교육, \t투자연계, \t피칭 \t전략, \t투자 \t및 \t생존전략.\n• \t법률 \t및 \t회계/세무: \t세무 \t교육 \t(부가세 \t신고, \t인건비 \t지급 \t등), \t회계, \t비용 \t쓰는 \t방법,\n서류 \t작성.\n• \t실무적 \t지원: \t시제품 \t제작, \t실무적 \t교육, \t정부지원사업 \t연계 \t전략, \t글로벌지원팀, \t마케팅",
      "firstLine": "- \t28 \t-"
    },
    {
      "pageNumber": 29,
      "text": "- \t29 \t-\n지원, \tR&D, \t외주 \t기업 \t매칭, \t온라인 \t최적화 \t프로그램 \t교육, \t1:1 \t코칭 \t비중 \t확대.\n• \t사업 \t고도화: \tBM \t정의하기, \t시장성과 \t사업성의 \t체계적인 \t검증.\n￿ \t제언\n• \t일정 \t및 \t시간 \t배분 \t재조정: \t현재의 \t촉박한 \t일정과 \t보고서 \t동시 \t작성 \t방식은 \t학습\n효과를 \t저해하는 \t주요 \t원인이므로, \t학습-보고서 \t작성 \t분리 \t또는 \t충분한 \t여유 \t시간\n확보하는 \t방식으로 \t고도화(코칭 \t시간 \t강화)\n• \tAI \t활용 \t교육 \t심화: \t참가자들의 \t추가 \t요구를 \t반영하여 \tAI \t활용 \t교육 \t콘텐츠를 \t통해\n다양한 \tAI의 \t활용도를 \t파악할 \t수 \t있는 \t교육도 \t도움이 \t될 \t것이라 \t판단\n• \t확장된 \t실무 \t교육 \t제공: \t투자, \t법률/세무, \t그리고 \t시제품 \t제작 \t등 \t실질적인 \t사업 \t운영에\n필요한 \t분야의 \t교육 \t및 \t지원도 \t필요하다는 \t것을 \t확인",
      "firstLine": "- \t29 \t-"
    }
  ],
  "extractedAt": "2026-05-30T06:52:54.762Z"
}