{
  "assetId": "cmpl8uhhm000jwkvcazrqyrrb",
  "name": "DOGS 성향 진단 모델: 1만 명의 창업가 데이터를 기반으로 한 팀빌딩 솔루션",
  "fileName": "07. 일어_OD 삽살개.pptx",
  "mimeType": "application/vnd.openxmlformats-officedocument.presentationml.presentation",
  "sizeMB": 3.9,
  "kind": "pptx",
  "totalSlides": 12,
  "totalShapes": 284,
  "slides": [
    {
      "slideNumber": 1,
      "shapes": [
        {
          "type": "shape",
          "position": {
            "x": 0.025749917979002626,
            "y": 0.7128887430737825,
            "w": 0.38604166666666667,
            "h": 0.002685185185185185
          },
          "fillColor": "000000",
          "strokeColor": "000000"
        },
        {
          "type": "shape",
          "geomPreset": "rect",
          "position": {
            "x": 0.3579583333333333,
            "y": 0.03325925925925926,
            "w": 0.054739583333333335,
            "h": 0.023981481481481482
          },
          "text": "DOGSTEST",
          "fontSize": 9
        },
        {
          "type": "shape",
          "geomPreset": "rect",
          "position": {
            "x": 0.02470825131233596,
            "y": 0.4311258384368621,
            "w": 0.18260416666666668,
            "h": 0.10350102070574511
          },
          "text": "あなたは客観的な資料を土台に仕事をするサプサル犬です",
          "fontSize": 14
        },
        {
          "type": "shape",
          "position": {
            "x": 0.02575,
            "y": 0.6262220764071158,
            "w": 0.15276041666666668,
            "h": 0.030740740740740742
          },
          "fillColor": "000000",
          "strokeColor": "000000"
        },
        {
          "type": "shape",
          "geomPreset": "rect",
          "position": {
            "x": 0.03216535433070866,
            "y": 0.6279257801108195,
            "w": 0.13942708333333334,
            "h": 0.02702055993000875
          },
          "text": "挑戦     正確性     結果志向",
          "fillColor": "7789B8",
          "strokeColor": "7789B8",
          "textColor": "7789B8",
          "fontSize": 11
        },
        {
          "type": "shape",
          "geomPreset": "rect",
          "position": {
            "x": 0.02470825131233596,
            "y": 0.7194813356663751,
            "w": 0.07416666666666667,
            "h": 0.022719743365412656
          },
          "text": "タイプ別回答結果",
          "fontSize": 9
        },
        {
          "type": "shape",
          "geomPreset": "rect",
          "position": {
            "x": 0.347875,
            "y": 0.7194814814814815,
            "w": 0.06503125,
            "h": 0.01851239428404783
          },
          "text": "スコア合算：69点",
          "fontSize": 7.5
        },
        {
          "type": "shape",
          "geomPreset": "rect",
          "position": {
            "x": 0.02420242782152231,
            "y": 0.09903689122193059,
            "w": 0.2382975721784777,
            "h": 0.04553295421405658
          },
          "text": "DOGS タイプテスト結果紙",
          "placeholderType": "title"
        },
        {
          "type": "shape",
          "position": {
            "x": 0.02575,
            "y": 1.036,
            "w": 0.09651041666666667,
            "h": 0.03777763196267133
          },
          "fillColor": "000000",
          "strokeColor": "000000"
        },
        {
          "type": "shape",
          "geomPreset": "rect",
          "position": {
            "x": 0.05120825131233596,
            "y": 1.040370224555264,
            "w": 0.043958333333333335,
            "h": 0.02879702537182852
          },
          "text": "D:管理",
          "fontSize": 12
        },
        {
          "type": "shape",
          "geomPreset": "rect",
          "position": {
            "x": 0.06558325131233596,
            "y": 0.7630368912219306,
            "w": 0.016875,
            "h": 0.030370224555263926
          },
          "text": "18",
          "fontSize": 12
        },
        {
          "type": "shape",
          "position": {
            "x": 0.058375,
            "y": 0.8017776319626714,
            "w": 0.16041666666666668,
            "h": 0.272037037037037
          },
          "fillColor": "000000",
          "strokeColor": "000000"
        },
        {
          "type": "shape",
          "geomPreset": "rect",
          "position": {
            "x": 0.12149991797900263,
            "y": 1.0373331875182268,
            "w": 0.09651041666666667,
            "h": 0.031882473024205306
          },
          "text": "O:思考",
          "fillColor": "000000",
          "strokeColor": "000000",
          "fontSize": 12
        },
        {
          "type": "shape",
          "geomPreset": "rect",
          "position": {
            "x": 0.16208333333333333,
            "y": 0.7630368912219306,
            "w": 0.016875,
            "h": 0.030370224555263926
          },
          "text": "18",
          "fontSize": 12
        },
        {
          "type": "shape",
          "position": {
            "x": 0.154875,
            "y": 0.8017776319626714,
            "w": 0.16041666666666668,
            "h": 0.272037037037037
          },
          "fillColor": "000000",
          "strokeColor": "000000"
        },
        {
          "type": "shape",
          "geomPreset": "rect",
          "position": {
            "x": 0.21875,
            "y": 1.040370224555264,
            "w": 0.095,
            "h": 0.02879702537182852
          },
          "text": "G:案内",
          "fontSize": 12
        },
        {
          "type": "shape",
          "geomPreset": "rect",
          "position": {
            "x": 0.25858333333333333,
            "y": 0.7937037037037037,
            "w": 0.016875,
            "h": 0.030370224555263926
          },
          "text": "1G",
          "fontSize": 12
        },
        {
          "type": "shape",
          "position": {
            "x": 0.251375,
            "y": 0.832444298629338,
            "w": 0.16041666666666668,
            "h": 0.24138888888888888
          },
          "fillColor": "000000",
          "strokeColor": "000000"
        },
        {
          "type": "shape",
          "geomPreset": "rect",
          "position": {
            "x": 0.34208325131233597,
            "y": 1.040370224555264,
            "w": 0.0428125,
            "h": 0.02879702537182852
          },
          "text": "S:支援",
          "fontSize": 12
        },
        {
          "type": "shape",
          "geomPreset": "rect",
          "position": {
            "x": 0.3550833333333333,
            "y": 0.7799259259259259,
            "w": 0.016875,
            "h": 0.030370224555263926
          },
          "text": "17",
          "fontSize": 12
        },
        {
          "type": "shape",
          "position": {
            "x": 0.347875,
            "y": 0.8186665208515602,
            "w": 0.03125,
            "h": 0.21916666666666668
          },
          "fillColor": "000000",
          "strokeColor": "000000"
        },
        {
          "type": "pic",
          "geomPreset": "rect",
          "position": {
            "x": 0,
            "y": 0,
            "w": 0.4374999179790026,
            "h": 1.1013331875182268
          }
        },
        {
          "type": "pic",
          "geomPreset": "rect",
          "position": {
            "x": 0.025749917979002626,
            "y": 0.036,
            "w": 0.05299991797900262,
            "h": 0.016444298629337998
          }
        },
        {
          "type": "pic",
          "geomPreset": "rect",
          "position": {
            "x": 0.21875,
            "y": 0.408444298629338,
            "w": 0.19299991797900262,
            "h": 0.304444298629338
          }
        },
        {
          "type": "pic",
          "geomPreset": "rect",
          "position": {
            "x": 0,
            "y": 1.1013331875182268,
            "w": 0.4374999179790026,
            "h": 0.0004442986293379994
          }
        },
        {
          "type": "table",
          "position": {
            "x": 0,
            "y": 0,
            "w": 1,
            "h": 1
          },
          "text": "氏名コードOD所属業務タイプサプサル犬 日付リーダーシップタイプ断固型",
          "fillColor": "000000",
          "strokeColor": "000000",
          "textColor": "000000",
          "fontSize": 10
        }
      ]
    },
    {
      "slideNumber": 2,
      "shapes": [
        {
          "type": "shape",
          "geomPreset": "rect",
          "position": {
            "x": 0.39945833333333336,
            "y": 0.03281481481481482,
            "w": 0.013333333333333334,
            "h": 0.023981481481481482
          },
          "text": "01",
          "fontSize": 9
        },
        {
          "type": "shape",
          "geomPreset": "rect",
          "position": {
            "x": 0.02420242782152231,
            "y": 0.09859244677748615,
            "w": 0.2132975721784777,
            "h": 0.08994400699912511
          },
          "text": "著作権に関する注意事項",
          "fontSize": 20,
          "placeholderType": "title"
        },
        {
          "type": "shape",
          "position": {
            "x": 0.02575,
            "y": 0.9226666666666666,
            "w": 0.38578125,
            "h": 0.13694444444444445
          },
          "fillColor": "000000",
          "strokeColor": "000000"
        },
        {
          "type": "shape",
          "geomPreset": "rect",
          "position": {
            "x": 0.01875,
            "y": 0.24544444444444444,
            "w": 0.38578125,
            "h": 0.3681437736949548
          },
          "text": "本作品の利用者は、クリエイティブ・コモンズ（CC）の「表示－非営利－継承 3.0」ライセンスの条件に従う必要があります。著作者または利用許可者が定めた方法で、本作品の原著作者を明示しなければなりません。(ただし、原著作者が利用者またはその利用を保証・推奨しているという意味で表示してはいけません）本作品を営利目的で利用することはできません。本作品を利用して作成した二次的著作物には、本ライセンスと同一のライセンスを適用する必要があります。",
          "fontSize": 10
        },
        {
          "type": "shape",
          "geomPreset": "rect",
          "position": {
            "x": 0.02446998031496063,
            "y": 0.939748031496063,
            "w": 0.05427985564304462,
            "h": 0.028909157188684746
          },
          "text": "発行者 :",
          "fontSize": 9
        },
        {
          "type": "shape",
          "geomPreset": "rect",
          "position": {
            "x": 0.02446998031496063,
            "y": 0.9782703412073491,
            "w": 0.07553001968503938,
            "h": 0.02887182852143482
          },
          "text": "プログラム名 :",
          "fontSize": 9
        },
        {
          "type": "shape",
          "geomPreset": "rect",
          "position": {
            "x": 0.02574983595800525,
            "y": 1.018940653251677,
            "w": 0.08675008202099738,
            "h": 0.02887182852143482
          },
          "text": "発行日 :",
          "fontSize": 9
        },
        {
          "type": "pic",
          "geomPreset": "rect",
          "position": {
            "x": 0,
            "y": 0,
            "w": 0.4374999179790026,
            "h": 1.1008887430737824
          }
        },
        {
          "type": "pic",
          "geomPreset": "rect",
          "position": {
            "x": 0.025749917979002626,
            "y": 0.035555555555555556,
            "w": 0.05299991797900262,
            "h": 0.016444298629337998
          }
        }
      ]
    },
    {
      "slideNumber": 3,
      "shapes": [
        {
          "type": "shape",
          "geomPreset": "rect",
          "position": {
            "x": 0.39945833333333336,
            "y": 0.03237022455526393,
            "w": 0.013333333333333334,
            "h": 0.023981481481481482
          },
          "text": "02",
          "fontSize": 9
        },
        {
          "type": "shape",
          "geomPreset": "rect",
          "position": {
            "x": 0.024202345800524935,
            "y": 0.09814814814814815,
            "w": 0.28369061679790025,
            "h": 0.1330459317585302
          },
          "text": "アンダードッグスワンチーム ソリューション紹介",
          "placeholderType": "title"
        },
        {
          "type": "shape",
          "geomPreset": "rect",
          "position": {
            "x": 0.02443290682414698,
            "y": 0.2558369787109945,
            "w": 0.32556709317585303,
            "h": 0.062455818022747155
          },
          "text": "アンダードッグスはワンチーム ソリューションを通じて組織の問題を共に悩み解決していきます。",
          "fontSize": 10.5
        },
        {
          "type": "shape",
          "position": {
            "x": 0.1460132874015748,
            "y": 0.43279833770778653,
            "w": 0.00546875,
            "h": 0.019537037037037037
          },
          "fillColor": "FA5433",
          "strokeColor": "FA5433"
        },
        {
          "type": "shape",
          "position": {
            "x": 0.2850132874015748,
            "y": 0.43279833770778653,
            "w": 0.00546875,
            "h": 0.019537037037037037
          },
          "fillColor": "FA5433",
          "strokeColor": "FA5433"
        },
        {
          "type": "shape",
          "geomPreset": "rect",
          "position": {
            "x": 0.02451492782152231,
            "y": 0.5368148148148149,
            "w": 0.3929463582677165,
            "h": 0.4956265675123943
          },
          "text": "ワンチーム ソリューション ヒストリー 1万人に近い起業家を教育しながら見つけた持続可能なチームの条件アンダードッグスは2016年から1万人に近い起業家を教育してきました。起業家がチームを組む過程からスタートアップ として成長していく過程まで、6年間共に走ってきました。多様な性格のチームに出会いながら悟った一つのことがあるとすれば、 「いくら構成員それぞれの力量が優れていても個々人の特性に対する深い理解がなければチームは壊れるもの」ということ です。 性格と性向を基盤に探していくチームビルディング ソリューションアンダードッグスは性格と業務性向を基盤としたチームビルディングの重要性を常に強調してきました。力量と職務と同じくらい組織に おいては各個人の性向と価値観を理解することが重要です。同一の職務であっても、個々人の性向と価値観によって チームに異なる影響を及ぼすからです。本人の性向と同僚の性向を知れば、不要な摩擦を防止しシナジーを 出しながら組織目標により近づくことができるのではないでしょうか? 個人からチームへ、そして組織文化まで着実に積み上げられるようにアンダードッグスはチーム構成員が強みを強化し互いが弱みを補完する方向へ進めるように「ワンチーム ソリューション」を提案します。今読んでいるDOGS性向診断がその始まりです。性向診断を通じて互いの業務性 向を正確に把握すれば同僚たちとの協業がより円滑になるでしょう。次の段階ではDOGS対話カードを通じて互 いの性向と価値観をより深く理解することができ、ワークショップで健全な組織文化に一歩近づくことができます。ワンチーム ソリューションで皆さんの組織がより堅固になることを期待します。",
          "fontSize": 10
        },
        {
          "type": "shape",
          "geomPreset": "rect",
          "position": {
            "x": 0.018659284776902887,
            "y": 0.3411827063283756,
            "w": 0.22509071522309712,
            "h": 0.04039063867016623
          },
          "text": "ワンチーム ソリューション構成段階",
          "fontSize": 12
        },
        {
          "type": "shape",
          "position": {
            "x": 0.025749917979002626,
            "y": 0.440444298629338,
            "w": 0.10802083333333333,
            "h": 0.001388888888888889
          },
          "fillColor": "000000",
          "strokeColor": "000000"
        },
        {
          "type": "shape",
          "position": {
            "x": 0.02420242782152231,
            "y": 0.4469078448527267,
            "w": 0.10802083333333333,
            "h": 0.05333333333333334
          },
          "fillColor": "000000",
          "strokeColor": "000000"
        },
        {
          "type": "shape",
          "geomPreset": "rect",
          "position": {
            "x": 0.02496694553805774,
            "y": 0.399076990376203,
            "w": 0.10651041666666666,
            "h": 0.04535578885972587
          }
        },
        {
          "type": "shape",
          "geomPreset": "rect",
          "position": {
            "x": 0.027823326771653542,
            "y": 0.39946689997083695,
            "w": 0.10079757217847769,
            "h": 0.03590274132400117
          },
          "text": "業務性向診断",
          "fontSize": 10
        },
        {
          "type": "shape",
          "geomPreset": "rect",
          "position": {
            "x": 0.027823326771653542,
            "y": 0.45092592592592595,
            "w": 0.10001451771653544,
            "h": 0.04936628754738991
          },
          "text": "DOGS 性向診断",
          "fontSize": 8
        },
        {
          "type": "shape",
          "position": {
            "x": 0.1611290190288714,
            "y": 0.4327528433945757,
            "w": 0.10802083333333333,
            "h": 0.001388888888888889
          },
          "fillColor": "000000",
          "strokeColor": "000000"
        },
        {
          "type": "shape",
          "position": {
            "x": 0.15958152887139107,
            "y": 0.43921638961796444,
            "w": 0.10802083333333333,
            "h": 0.05333333333333334
          },
          "fillColor": "000000",
          "strokeColor": "000000"
        },
        {
          "type": "shape",
          "geomPreset": "rect",
          "position": {
            "x": 0.1603460465879265,
            "y": 0.39138553514144064,
            "w": 0.10651041666666666,
            "h": 0.04535578885972587
          }
        },
        {
          "type": "shape",
          "geomPreset": "rect",
          "position": {
            "x": 0.16109194553805775,
            "y": 0.3848923884514436,
            "w": 0.10540223097112861,
            "h": 0.05834208223972003
          },
          "text": "ネットワーキング・チームビルディング",
          "fontSize": 10
        },
        {
          "type": "shape",
          "geomPreset": "rect",
          "position": {
            "x": 0.16162319553805773,
            "y": 0.44155978419364245,
            "w": 0.10001451771653544,
            "h": 0.044878536016331294
          },
          "text": "DOGS対話カード",
          "fontSize": 7
        },
        {
          "type": "shape",
          "position": {
            "x": 0.30944045275590554,
            "y": 0.4379692330125401,
            "w": 0.10802083333333333,
            "h": 0.001388888888888889
          },
          "fillColor": "000000",
          "strokeColor": "000000"
        },
        {
          "type": "shape",
          "position": {
            "x": 0.3078929625984252,
            "y": 0.44443277923592883,
            "w": 0.10802083333333333,
            "h": 0.05333333333333334
          },
          "fillColor": "000000",
          "strokeColor": "000000"
        },
        {
          "type": "shape",
          "geomPreset": "rect",
          "position": {
            "x": 0.30865748031496065,
            "y": 0.3966019247594051,
            "w": 0.10651041666666666,
            "h": 0.04535578885972587
          }
        },
        {
          "type": "shape",
          "geomPreset": "rect",
          "position": {
            "x": 0.3115138615485564,
            "y": 0.39010877806940797,
            "w": 0.10079757217847769,
            "h": 0.05834208223972003
          },
          "text": "ワークショッププログラム",
          "fontSize": 10
        },
        {
          "type": "shape",
          "geomPreset": "rect",
          "position": {
            "x": 0.3105486384514436,
            "y": 0.4449396325459318,
            "w": 0.10001451771653544,
            "h": 0.06058588509769612
          },
          "text": "ワークショッププログラムリーダーシップ／組織文化 など",
          "fontSize": 7
        },
        {
          "type": "pic",
          "geomPreset": "rect",
          "position": {
            "x": 0.025749917979002626,
            "y": 0.035110965296004666,
            "w": 0.05299991797900262,
            "h": 0.016444298629337998
          }
        }
      ]
    },
    {
      "slideNumber": 4,
      "shapes": [
        {
          "type": "shape",
          "geomPreset": "rect",
          "position": {
            "x": 0.39945833333333336,
            "y": 0.03192578011081948,
            "w": 0.013333333333333334,
            "h": 0.023981481481481482
          },
          "text": "03",
          "fontSize": 9
        },
        {
          "type": "shape",
          "geomPreset": "rect",
          "position": {
            "x": 0.02420242782152231,
            "y": 0.13455322251385243,
            "w": 0.2945475721784777,
            "h": 0.08186585010207058
          },
          "text": "診断モデルDOGS 性向診断とは何でしょうか？",
          "fontSize": 18
        },
        {
          "type": "shape",
          "geomPreset": "rect",
          "position": {
            "x": 0.024708169291338584,
            "y": 0.23885928842228055,
            "w": 0.3880834153543307,
            "h": 0.10275298920968212
          },
          "text": "アンダードッグスは、業務傾向を管理型（Director）、思考型（Organizer）、案内型（Guider）、支援型（Supporter）の4タイプに分類し、それぞれの頭文字を取って「DOGS 診断モデル」を作成しました。下の図を通して、外向／内向、関係志向／成果志向、そして各タイプ間の相互関係を一目で把握することができます。",
          "fontSize": 9
        },
        {
          "type": "shape",
          "geomPreset": "flowChartTerminator",
          "position": {
            "x": 0.024708169291338584,
            "y": 0.06937576552930884,
            "w": 0.08675,
            "h": 0.04273724117818606
          },
          "text": "診断モデル",
          "fontSize": 9
        },
        {
          "type": "shape",
          "geomPreset": "rect",
          "position": {
            "x": 0.2125,
            "y": 0.0901480023330417,
            "w": 0.19846875,
            "h": 0.0222522601341499
          },
          "text": "＋ 参加者の結果タイプは別の色で表示されます。",
          "fillColor": "8387B6",
          "strokeColor": "8387B6",
          "textColor": "8387B6",
          "fontSize": 9
        },
        {
          "type": "shape",
          "geomPreset": "rect",
          "position": {
            "x": 0,
            "y": 0,
            "w": 1,
            "h": 1
          },
          "text": "도베르만ドーベルマン비글ビーグル롯트와일러ロットワイラー비숑프리제ビション・フリーゼ푸들 プードル세인트 버나드 セントバーナード웰시코기ウェルシュコーギー골든리트리버ゴールデンレトリバー시츄シーズー진돗개 珍島犬（ちんとうけん）삽살개 サプサル犬 보더콜리ボーダーコリー"
        },
        {
          "type": "shape",
          "geomPreset": "rect",
          "position": {
            "x": 0.05572941272965879,
            "y": 0.447305045202683,
            "w": 0.05303018372703412,
            "h": 0.03292782152230971
          },
          "text": "強化関係",
          "fontSize": 9
        },
        {
          "type": "shape",
          "geomPreset": "rect",
          "position": {
            "x": 0.3275208333333333,
            "y": 0.44787941090697,
            "w": 0.04861368110236221,
            "h": 0.03292782152230971
          },
          "text": "強化関係",
          "fontSize": 8
        },
        {
          "type": "shape",
          "geomPreset": "rect",
          "position": {
            "x": 0.33058464566929135,
            "y": 0.925597987751531,
            "w": 0.04861368110236221,
            "h": 0.03292782152230971
          },
          "text": "強化関係",
          "fontSize": 8
        },
        {
          "type": "shape",
          "geomPreset": "rect",
          "position": {
            "x": 0.05937360564304462,
            "y": 0.9322150772820064,
            "w": 0.04861368110236221,
            "h": 0.03292782152230971
          },
          "text": "強化関係",
          "fontSize": 8
        },
        {
          "type": "shape",
          "geomPreset": "rect",
          "position": {
            "x": 0.25625,
            "y": 0.6398148148148148,
            "w": 0.04375,
            "h": 0.022222222222222223
          },
          "text": "案内型",
          "fontSize": 9
        },
        {
          "type": "shape",
          "geomPreset": "rect",
          "position": {
            "x": 0.13750008202099737,
            "y": 0.6398148148148148,
            "w": 0.04375,
            "h": 0.022222222222222223
          },
          "text": "管理型",
          "fontSize": 9
        },
        {
          "type": "shape",
          "geomPreset": "rect",
          "position": {
            "x": 0.14375,
            "y": 0.8175925925925925,
            "w": 0.04375,
            "h": 0.022222222222222223
          },
          "text": "思考型",
          "fontSize": 9
        },
        {
          "type": "shape",
          "geomPreset": "rect",
          "position": {
            "x": 0.24843766404199474,
            "y": 0.8175925925925925,
            "w": 0.04375,
            "h": 0.022222222222222223
          },
          "text": "支援型",
          "fontSize": 9
        },
        {
          "type": "shape",
          "geomPreset": "rect",
          "position": {
            "x": 0.19140600393700788,
            "y": 0.6953703703703704,
            "w": 0.05468766404199475,
            "h": 0.03333333333333333
          },
          "text": "補完関係",
          "fontSize": 9
        },
        {
          "type": "pic",
          "geomPreset": "rect",
          "position": {
            "x": 0.025749917979002626,
            "y": 0.3631111111111111,
            "w": 0.3859999179790026,
            "h": 0.6862220764071157
          }
        },
        {
          "type": "pic",
          "geomPreset": "rect",
          "position": {
            "x": 0.025749917979002626,
            "y": 0.034666520851560224,
            "w": 0.05299991797900262,
            "h": 0.016444298629337998
          }
        }
      ]
    },
    {
      "slideNumber": 5,
      "shapes": [
        {
          "type": "shape",
          "position": {
            "x": 0.074,
            "y": 0.396444298629338,
            "w": 0.14052083333333334,
            "h": 0.001388888888888889
          },
          "fillColor": "A588C0",
          "strokeColor": "A588C0"
        },
        {
          "type": "shape",
          "position": {
            "x": 0.074,
            "y": 0.3964461942257218,
            "w": 0.14052083333333334,
            "h": 0.2777777777777778
          },
          "fillColor": "A588C0",
          "strokeColor": "A588C0"
        },
        {
          "type": "shape",
          "position": {
            "x": 0.21824991797900262,
            "y": 0.6799998541848935,
            "w": 0.00078125,
            "h": 0.001388888888888889
          },
          "fillColor": "000000",
          "strokeColor": "000000"
        },
        {
          "type": "shape",
          "position": {
            "x": 0.21862491797900263,
            "y": 0.3355554097404491,
            "w": 0,
            "h": 0.34444444444444444
          },
          "fillColor": "000000",
          "strokeColor": "000000"
        },
        {
          "type": "shape",
          "position": {
            "x": 0.223,
            "y": 0.396444298629338,
            "w": 0.14052083333333334,
            "h": 0.001388888888888889
          },
          "fillColor": "000000",
          "strokeColor": "000000"
        },
        {
          "type": "shape",
          "position": {
            "x": 0.223,
            "y": 0.3964461942257218,
            "w": 0.14052083333333334,
            "h": 0.2777777777777778
          },
          "fillColor": "12A84E",
          "strokeColor": "12A84E"
        },
        {
          "type": "shape",
          "position": {
            "x": 0.21375,
            "y": 0.6813331875182269,
            "w": 0.00078125,
            "h": 0.001388888888888889
          },
          "fillColor": "000000",
          "strokeColor": "000000"
        },
        {
          "type": "shape",
          "position": {
            "x": 0.07475,
            "y": 0.6819998541848935,
            "w": 0.13901033464566928,
            "h": 0
          },
          "fillColor": "000000",
          "strokeColor": "000000"
        },
        {
          "type": "shape",
          "position": {
            "x": 0.2145,
            "y": 0.6813331875182269,
            "w": 0.00078125,
            "h": 0.001388888888888889
          },
          "fillColor": "000000",
          "strokeColor": "000000"
        },
        {
          "type": "shape",
          "position": {
            "x": 0.22224991797900262,
            "y": 0.6813331875182269,
            "w": 0.00078125,
            "h": 0.001388888888888889
          },
          "fillColor": "000000",
          "strokeColor": "000000"
        },
        {
          "type": "shape",
          "position": {
            "x": 0.21524991797900261,
            "y": 0.6819998541848935,
            "w": 0.00703125,
            "h": 0
          },
          "fillColor": "000000",
          "strokeColor": "000000"
        },
        {
          "type": "shape",
          "position": {
            "x": 0.22299991797900262,
            "y": 0.6813331875182269,
            "w": 0.00078125,
            "h": 0.001388888888888889
          },
          "fillColor": "000000",
          "strokeColor": "000000"
        },
        {
          "type": "shape",
          "position": {
            "x": 0.36274991797900263,
            "y": 0.6813331875182269,
            "w": 0.00078125,
            "h": 0.001388888888888889
          },
          "fillColor": "000000",
          "strokeColor": "000000"
        },
        {
          "type": "shape",
          "position": {
            "x": 0.22374991797900262,
            "y": 0.6819998541848935,
            "w": 0.13901033464566928,
            "h": 0
          },
          "fillColor": "000000",
          "strokeColor": "000000"
        },
        {
          "type": "shape",
          "position": {
            "x": 0.074,
            "y": 0.7448887430737824,
            "w": 0.14052083333333334,
            "h": 0.001388888888888889
          },
          "fillColor": "000000",
          "strokeColor": "000000"
        },
        {
          "type": "shape",
          "position": {
            "x": 0.074,
            "y": 0.7448906386701662,
            "w": 0.14052083333333334,
            "h": 0.2777777777777778
          },
          "fillColor": "000000",
          "strokeColor": "000000"
        },
        {
          "type": "shape",
          "position": {
            "x": 0.21824991797900262,
            "y": 1.028444298629338,
            "w": 0.00078125,
            "h": 0.001388888888888889
          },
          "fillColor": "000000",
          "strokeColor": "000000"
        },
        {
          "type": "shape",
          "position": {
            "x": 0.21862491797900263,
            "y": 0.6839998541848935,
            "w": 0,
            "h": 0.34444444444444444
          },
          "fillColor": "000000",
          "strokeColor": "000000"
        },
        {
          "type": "shape",
          "position": {
            "x": 0.223,
            "y": 0.7448887430737824,
            "w": 0.14052083333333334,
            "h": 0.001388888888888889
          },
          "fillColor": "000000",
          "strokeColor": "000000"
        },
        {
          "type": "shape",
          "position": {
            "x": 0.223,
            "y": 0.7448906386701662,
            "w": 0.14052083333333334,
            "h": 0.2777777777777778
          },
          "fillColor": "000000",
          "strokeColor": "000000"
        },
        {
          "type": "shape",
          "geomPreset": "rect",
          "position": {
            "x": 0.39945833333333336,
            "y": 0.03148133566637504,
            "w": 0.013333333333333334,
            "h": 0.023981481481481482
          },
          "text": "04",
          "fontSize": 9
        },
        {
          "type": "shape",
          "geomPreset": "rect",
          "position": {
            "x": 0.032458251312335956,
            "y": 0.08925911344415281,
            "w": 0.06927083333333334,
            "h": 0.028796296296296296
          },
          "text": "4대 진단 유형",
          "fillColor": "FFFFFF",
          "strokeColor": "FFFFFF",
          "textColor": "FFFFFF",
          "fontSize": 11
        },
        {
          "type": "shape",
          "geomPreset": "rect",
          "position": {
            "x": 0.03745825131233596,
            "y": 0.667037037037037,
            "w": 0.03125,
            "h": 0.03111111111111111
          },
          "text": "Taskoriented",
          "fillColor": "333333",
          "strokeColor": "333333",
          "textColor": "333333",
          "fontSize": 6.5
        },
        {
          "type": "shape",
          "position": {
            "x": 0.21700377296587928,
            "y": 0.32619247594050743,
            "w": 0.00375,
            "h": 0.007222222222222222
          },
          "fillColor": "2A2D33",
          "strokeColor": "2A2D33"
        },
        {
          "type": "shape",
          "geomPreset": "rect",
          "position": {
            "x": 0.36895833333333333,
            "y": 0.667037037037037,
            "w": 0.03125,
            "h": 0.03111111111111111
          },
          "text": "Peopleoriented",
          "fillColor": "333333",
          "strokeColor": "333333",
          "textColor": "333333",
          "fontSize": 6.5
        },
        {
          "type": "shape",
          "geomPreset": "rect",
          "position": {
            "x": 0.074375,
            "y": 0.3408887430737824,
            "w": 0.1397915846456693,
            "h": 0.04740288713910761
          },
          "text": "管理型Director",
          "fontSize": 8
        },
        {
          "type": "shape",
          "geomPreset": "rect",
          "position": {
            "x": 0.223375,
            "y": 0.3408887430737824,
            "w": 0.1397915846456693,
            "h": 0.04740288713910761
          },
          "text": "案内型Guider",
          "fontSize": 8
        },
        {
          "type": "shape",
          "geomPreset": "rect",
          "position": {
            "x": 0.074375,
            "y": 0.6893331875182269,
            "w": 0.1397915846456693,
            "h": 0.04740288713910761
          },
          "text": "思考型Orginizer",
          "fillColor": "8387B6",
          "fontSize": 8
        },
        {
          "type": "shape",
          "geomPreset": "rect",
          "position": {
            "x": 0.223375,
            "y": 0.6893331875182269,
            "w": 0.1397915846456693,
            "h": 0.04740288713910761
          },
          "text": "支援型Supporter",
          "fillColor": "000000",
          "fontSize": 8
        },
        {
          "type": "shape",
          "geomPreset": "rect",
          "position": {
            "x": 0.20195833333333332,
            "y": 1.039037037037037,
            "w": 0.033541666666666664,
            "h": 0.018703703703703705
          },
          "text": "Reserved",
          "fillColor": "333333",
          "strokeColor": "333333",
          "textColor": "333333",
          "fontSize": 6.5
        },
        {
          "type": "shape",
          "position": {
            "x": 0.07010826771653543,
            "y": 0.6788887430737824,
            "w": 0.0040625,
            "h": 0.006666666666666667
          },
          "fillColor": "2A2D33",
          "strokeColor": "2A2D33"
        },
        {
          "type": "shape",
          "position": {
            "x": 0.3633572834645669,
            "y": 0.6788955963837854,
            "w": 0.0040625,
            "h": 0.006666666666666667
          },
          "fillColor": "2A2D33",
          "strokeColor": "2A2D33"
        },
        {
          "type": "shape",
          "position": {
            "x": 0.21699991797900262,
            "y": 1.0306351706036745,
            "w": 0.00375,
            "h": 0.007222222222222222
          },
          "fillColor": "2A2D33",
          "strokeColor": "2A2D33"
        },
        {
          "type": "shape",
          "geomPreset": "rect",
          "position": {
            "x": 0.02420242782152231,
            "y": 0.1338127734033246,
            "w": 0.27579757217847767,
            "h": 0.039857830271216095
          },
          "text": "DOGS 性向別特徴は何ですか?",
          "fontSize": 18,
          "placeholderType": "title"
        },
        {
          "type": "shape",
          "geomPreset": "rect",
          "position": {
            "x": 0.02470825131233596,
            "y": 0.19537037037037036,
            "w": 0.38640625,
            "h": 0.08255774278215224
          },
          "text": "業務時、問題自体に焦点を合わせるか、問題の周辺関係に集中するか、その過程で状況にどのような方式で対応するかによって業務性向は大きく4つに区分されます。診断を通じて業務時の主要動機と好み及び回避環境、長・短所を把握することができ、性向把握に役立ちます。",
          "fontSize": 9
        },
        {
          "type": "shape",
          "geomPreset": "flowChartTerminator",
          "position": {
            "x": 0.02575,
            "y": 0.06937576552930884,
            "w": 0.08675,
            "h": 0.04273724117818606
          },
          "text": "4大診断タイプ",
          "fontSize": 9
        },
        {
          "type": "shape",
          "geomPreset": "rect",
          "position": {
            "x": 0.0745754593175853,
            "y": 0.4351010498687664,
            "w": 0.13901033464566928,
            "h": 0.1956888305628463
          },
          "text": "結果を達成するために競争を克服することで自ら環境を造成する速く結果を得る他の人の行動を誘発させる挑戦を受け入れる意思決定を速く下す既存の状態に問題を提起する指導力を発揮する難しい問題を処理する",
          "fontSize": 6
        },
        {
          "type": "shape",
          "geomPreset": "rect",
          "position": {
            "x": 0.22351640419947508,
            "y": 0.434558326042578,
            "w": 0.13901033464566928,
            "h": 0.2159870224555264
          },
          "text": "他の人を説得したり影響を及ぼすことで自ら環境を造成する人々と接触する肯定的な印象を与える話術がある他の人を動機付けする情熱的である人々を楽しませる人と状況に対して楽観的であるグループ活動を好む",
          "fontSize": 6
        },
        {
          "type": "shape",
          "geomPreset": "rect",
          "position": {
            "x": 0.075,
            "y": 0.7871808107319919,
            "w": 0.13901033464566928,
            "h": 0.21458457276173812
          },
          "text": "業務の品質と正確性を高めるために既存の環境の中で慎重に仕事をする重要な指示や基準に関心を持つ細部事項に気を配る分析的に思考し総合的等を考慮する外交的手腕がある葛藤に対して間接的或いは迂回的に接近する正確性を点検する業務遂行に対して批評的に分析する",
          "fontSize": 6
        },
        {
          "type": "shape",
          "geomPreset": "rect",
          "position": {
            "x": 0.2355,
            "y": 0.7733398950131234,
            "w": 0.13901033464566928,
            "h": 0.24020268299795858
          },
          "text": "関心を遂行するために他の人と協力する予測可能で一貫性のある仕事を遂行する忍耐力を示す専門的な技術を開発する他の人を聞いて支援する忠誠心を示す人の話をよく聞く動揺した人を落ち着かせる安定して調和のとれた業務環境を作る",
          "fontSize": 6
        },
        {
          "type": "pic",
          "geomPreset": "rect",
          "position": {
            "x": 0.025749917979002626,
            "y": 0.034222076407115776,
            "w": 0.05299991797900262,
            "h": 0.016444298629337998
          }
        }
      ]
    },
    {
      "slideNumber": 6,
      "shapes": [
        {
          "type": "shape",
          "geomPreset": "rect",
          "position": {
            "x": 0.39945833333333336,
            "y": 0.031037037037037037,
            "w": 0.013333333333333334,
            "h": 0.023981481481481482
          },
          "text": "05",
          "fontSize": 9
        },
        {
          "type": "shape",
          "geomPreset": "rect",
          "position": {
            "x": 0.02420242782152231,
            "y": 0.17215923009623796,
            "w": 0.3195475721784777,
            "h": 0.039754884806065906
          },
          "text": "DOGS タイプ詳細特徴は何ですか?",
          "fontSize": 18,
          "placeholderType": "title"
        },
        {
          "type": "shape",
          "geomPreset": "rect",
          "position": {
            "x": 0.02470825131233596,
            "y": 0.2491875182268883,
            "w": 0.38505208333333335,
            "h": 0.08255774278215224
          },
          "text": "4大診断タイプはより具体的な特徴を持つ12個の詳細タイプに分かれます。例えば、同じ案内型の中でも案内型特徴のみを持つプードル(GG)、案内型+管理型特徴を持つビション・フリーゼ(GD)、案内型+支援型のセントバーナード(GS)で構成されます。12種各タイプは類似したイメージを持つ犬(dogs)の種類で表現されます。",
          "fontSize": 9
        },
        {
          "type": "shape",
          "geomPreset": "rect",
          "position": {
            "x": 0.02821998031496063,
            "y": 0.40586730825313505,
            "w": 0.06973958333333333,
            "h": 0.0825
          },
          "text": "D管理型 Director",
          "fontSize": 18
        },
        {
          "type": "shape",
          "geomPreset": "rect",
          "position": {
            "x": 0.22621998031496063,
            "y": 0.40586730825313505,
            "w": 0.07479166666666667,
            "h": 0.08227719451735199
          },
          "text": "O思考型 Organizer",
          "fillColor": "8387B6",
          "strokeColor": "8387B6",
          "textColor": "8387B6",
          "fontSize": 18
        },
        {
          "type": "shape",
          "geomPreset": "rect",
          "position": {
            "x": 0.02845825131233596,
            "y": 0.5259703995333916,
            "w": 0.18526041666666668,
            "h": 0.05154491105278507
          },
          "text": "速く目標を達成するために自ら環境を造成し指導力を発揮し、難しい問題を処理するタイプ",
          "fontSize": 9
        },
        {
          "type": "shape",
          "geomPreset": "rect",
          "position": {
            "x": 0.22645825131233596,
            "y": 0.5259703995333916,
            "w": 0.17635416666666667,
            "h": 0.06423228346456693
          },
          "text": "クオリティと正確性を高めるために慎重で綿密に仕事をし、業務と関係において分析的に思考するタイプ",
          "fillColor": "333333",
          "textColor": "333333",
          "fontSize": 9
        },
        {
          "type": "shape",
          "geomPreset": "rect",
          "position": {
            "x": 0.09698958333333334,
            "y": 0.6183855351414407,
            "w": 0.11848958333333333,
            "h": 0.06270836978710995
          },
          "text": "ドーベルマン エネルギーに溢れ競争心が非常に強いタイプ",
          "fontSize": 7.5
        },
        {
          "type": "shape",
          "position": {
            "x": 0.2935,
            "y": 0.6946665208515602,
            "w": 0.1,
            "h": 0.02185185185185185
          },
          "fillColor": "000000",
          "strokeColor": "000000"
        },
        {
          "type": "shape",
          "geomPreset": "rect",
          "position": {
            "x": 0.29601492782152233,
            "y": 0.6213480606590843,
            "w": 0.1021875,
            "h": 0.06282064741907262
          },
          "text": "ボーダーコリー エネルギーに溢れ競争心が非常に強いタイプ",
          "fillColor": "333333",
          "strokeColor": "333333",
          "textColor": "333333",
          "fontSize": 7.5
        },
        {
          "type": "shape",
          "geomPreset": "rect",
          "position": {
            "x": 0.09801492782152231,
            "y": 0.7346813939924176,
            "w": 0.11119791666666666,
            "h": 0.06271770195392243
          },
          "text": "ビーグル 本人と周辺の人々を管理するのに長けたタイプ",
          "fontSize": 7.5
        },
        {
          "type": "shape",
          "position": {
            "x": 0.2935,
            "y": 0.808,
            "w": 0.1075,
            "h": 0.02185185185185185
          },
          "fillColor": "8387B6",
          "strokeColor": "8387B6"
        },
        {
          "type": "shape",
          "geomPreset": "rect",
          "position": {
            "x": 0.29601492782152233,
            "y": 0.7346813939924176,
            "w": 0.10947916666666667,
            "h": 0.06282064741907262
          },
          "text": "サプサル犬 直観的で客観的な資料を土台に効率的に仕事をするタイプ",
          "fillColor": "8387B6",
          "strokeColor": "8387B6",
          "textColor": "8387B6",
          "fontSize": 7.5
        },
        {
          "type": "shape",
          "geomPreset": "rect",
          "position": {
            "x": 0.09801492782152231,
            "y": 0.8480147273257509,
            "w": 0.11848958333333333,
            "h": 0.06282064741907262
          },
          "text": "ロットワイラー 高い基準と決定力で仕事を推進していくタイプ",
          "fillColor": "333333",
          "strokeColor": "333333",
          "textColor": "333333",
          "fontSize": 7.5
        },
        {
          "type": "shape",
          "position": {
            "x": 0.2935,
            "y": 0.9213331875182269,
            "w": 0.1,
            "h": 0.02185185185185185
          },
          "fillColor": "000000",
          "strokeColor": "000000"
        },
        {
          "type": "shape",
          "geomPreset": "rect",
          "position": {
            "x": 0.29601492782152233,
            "y": 0.8480147273257509,
            "w": 0.10947916666666667,
            "h": 0.06282064741907262
          },
          "text": "珍島犬 体系的で正確に考えて仕事をするタイプ",
          "fillColor": "333333",
          "strokeColor": "333333",
          "textColor": "333333",
          "fontSize": 7.5
        },
        {
          "type": "shape",
          "geomPreset": "flowChartTerminator",
          "position": {
            "x": 0.02420242782152231,
            "y": 0.09214858559346749,
            "w": 0.08675,
            "h": 0.04273724117818606
          },
          "text": "詳細診断タイプ",
          "fontSize": 9
        },
        {
          "type": "shape",
          "geomPreset": "rect",
          "position": {
            "x": 0.06200951443569554,
            "y": 0.6904906678331875,
            "w": 0.21875,
            "h": 0.03141498979294255
          },
          "text": "成果       行動        挑戦",
          "fontSize": 8
        },
        {
          "type": "shape",
          "geomPreset": "rect",
          "position": {
            "x": 0.07414583333333333,
            "y": 0.8037500729075532,
            "w": 0.21875,
            "h": 0.03141498979294255
          },
          "text": "行動         成果         協定",
          "fontSize": 8
        },
        {
          "type": "shape",
          "geomPreset": "rect",
          "position": {
            "x": 0.0757550032808399,
            "y": 0.9175925925925926,
            "w": 0.21875,
            "h": 0.03141498979294255
          },
          "text": "挑戦          成果        正確性",
          "fontSize": 8
        },
        {
          "type": "shape",
          "geomPreset": "rect",
          "position": {
            "x": 0.2807595144356955,
            "y": 0.6910554097404491,
            "w": 0.21875,
            "h": 0.03141498979294255
          },
          "text": "正確性       安定性        挑戦",
          "fontSize": 8
        },
        {
          "type": "shape",
          "geomPreset": "rect",
          "position": {
            "x": 0.2807595144356955,
            "y": 0.8042591134441528,
            "w": 0.21875,
            "h": 0.03141498979294255
          },
          "text": "挑戦         正確性        結果志向",
          "fontSize": 8
        },
        {
          "type": "shape",
          "geomPreset": "rect",
          "position": {
            "x": 0.28365608595800523,
            "y": 0.9188509769612132,
            "w": 0.21875,
            "h": 0.03141498979294255
          },
          "text": "安定性          正確性        支持",
          "fontSize": 8
        },
        {
          "type": "pic",
          "geomPreset": "rect",
          "position": {
            "x": 0.025749917979002626,
            "y": 0.033777631962671334,
            "w": 0.05299991797900262,
            "h": 0.016444298629337998
          }
        },
        {
          "type": "pic",
          "geomPreset": "rect",
          "position": {
            "x": 0.22749991797900262,
            "y": 0.6244441528142316,
            "w": 0.05849991797900263,
            "h": 0.09288874307378245
          }
        },
        {
          "type": "pic",
          "geomPreset": "rect",
          "position": {
            "x": 0.22749991797900262,
            "y": 0.8511108194808982,
            "w": 0.05849991797900263,
            "h": 0.09288874307378245
          }
        },
        {
          "type": "pic",
          "geomPreset": "rect",
          "position": {
            "x": 0.029499917979002626,
            "y": 0.6244441528142316,
            "w": 0.05849991797900263,
            "h": 0.09288874307378245
          }
        },
        {
          "type": "pic",
          "geomPreset": "rect",
          "position": {
            "x": 0.029499917979002626,
            "y": 0.7377776319626713,
            "w": 0.05849991797900263,
            "h": 0.09288874307378245
          }
        },
        {
          "type": "pic",
          "geomPreset": "rect",
          "position": {
            "x": 0.029499917979002626,
            "y": 0.8511108194808982,
            "w": 0.05849991797900263,
            "h": 0.09288874307378245
          }
        },
        {
          "type": "pic",
          "geomPreset": "rect",
          "position": {
            "x": 0.22749991797900262,
            "y": 0.7377776319626713,
            "w": 0.05849991797900263,
            "h": 0.09288874307378245
          }
        }
      ]
    },
    {
      "slideNumber": 7,
      "shapes": [
        {
          "type": "shape",
          "geomPreset": "rect",
          "position": {
            "x": 0.39945833333333336,
            "y": 0.03059259259259259,
            "w": 0.013333333333333334,
            "h": 0.0222522601341499
          },
          "text": "06",
          "fontSize": 9
        },
        {
          "type": "shape",
          "geomPreset": "rect",
          "position": {
            "x": 0.02821998031496063,
            "y": 0.24942300962379702,
            "w": 0.0628125,
            "h": 0.08227719451735199
          },
          "text": "G案内型 Guider",
          "fontSize": 18
        },
        {
          "type": "shape",
          "geomPreset": "rect",
          "position": {
            "x": 0.22221998031496062,
            "y": 0.24942300962379702,
            "w": 0.07927075131233596,
            "h": 0.08227719451735199
          },
          "text": "S支援型 Supporter",
          "fillColor": "333333",
          "strokeColor": "333333",
          "textColor": "333333",
          "fontSize": 18
        },
        {
          "type": "shape",
          "geomPreset": "rect",
          "position": {
            "x": 0.02845825131233596,
            "y": 0.3509259259259259,
            "w": 0.18244791666666665,
            "h": 0.05154491105278507
          },
          "text": "好意的な印象と話術で円満な関係を維持し、他人を説得し動機を誘発するタイプ",
          "fontSize": 9
        },
        {
          "type": "shape",
          "geomPreset": "rect",
          "position": {
            "x": 0.22245825131233596,
            "y": 0.3509259259259259,
            "w": 0.18244791666666665,
            "h": 0.062362350539515894
          },
          "text": "忍耐心、忠誠心、専門性を土台に他の人々と協力し安定的で調和のとれた環境を造成するタイプ",
          "fontSize": 9
        },
        {
          "type": "shape",
          "geomPreset": "rect",
          "position": {
            "x": 0.09801492782152231,
            "y": 0.4649036162146398,
            "w": 0.11998482611548557,
            "h": 0.04248498104403616
          },
          "text": "プードル 高い社会的技術と魅力を持つタイプ",
          "fontSize": 7.5
        },
        {
          "type": "shape",
          "geomPreset": "rect",
          "position": {
            "x": 0.29201492782152233,
            "y": 0.4649036162146398,
            "w": 0.10947916666666667,
            "h": 0.055724117818606006
          },
          "text": "ゴールデンレトリバー一貫した業務遂行を持続するタイプ",
          "fontSize": 8
        },
        {
          "type": "shape",
          "position": {
            "x": 0.28949991797900265,
            "y": 0.5582222222222222,
            "w": 0.0275,
            "h": 0.02185185185185185
          },
          "fillColor": "000000",
          "strokeColor": "000000"
        },
        {
          "type": "shape",
          "position": {
            "x": 0.31974991797900265,
            "y": 0.5582222222222222,
            "w": 0.033541666666666664,
            "h": 0.02185185185185185
          },
          "fillColor": "000000",
          "strokeColor": "000000"
        },
        {
          "type": "shape",
          "position": {
            "x": 0.3559999179790026,
            "y": 0.5582222222222222,
            "w": 0.0275,
            "h": 0.02185185185185185
          },
          "fillColor": "000000",
          "strokeColor": "000000"
        },
        {
          "type": "shape",
          "position": {
            "x": 0.0955,
            "y": 0.6711109652960047,
            "w": 0.10151041666666667,
            "h": 0.02185185185185185
          },
          "fillColor": "F9C059",
          "strokeColor": "F9C059"
        },
        {
          "type": "shape",
          "geomPreset": "rect",
          "position": {
            "x": 0.09801492782152231,
            "y": 0.5977925051035288,
            "w": 0.11119791666666666,
            "h": 0.06282064741907262
          },
          "text": "ビション・フリーゼ 結果と共に目的を達成するために積極的に努力するタイプ",
          "fontSize": 7.5
        },
        {
          "type": "shape",
          "position": {
            "x": 0.2895,
            "y": 0.6711109652960047,
            "w": 0.08802083333333334,
            "h": 0.02185185185185185
          },
          "fillColor": "000000",
          "strokeColor": "000000"
        },
        {
          "type": "shape",
          "geomPreset": "rect",
          "position": {
            "x": 0.29201492782152233,
            "y": 0.5977925051035288,
            "w": 0.10947916666666667,
            "h": 0.055724117818606006
          },
          "text": "ウェルシュコーギー業務を分掌し管理すると同時に他人を配慮するタイプ",
          "fontSize": 8
        },
        {
          "type": "shape",
          "geomPreset": "rect",
          "position": {
            "x": 0.09801492782152231,
            "y": 0.7111258384368621,
            "w": 0.115,
            "h": 0.055724117818606006
          },
          "text": "セントバーナード人間関係で発生する問題解決に長けたタイプ",
          "fontSize": 8
        },
        {
          "type": "shape",
          "position": {
            "x": 0.2895,
            "y": 0.7844444444444445,
            "w": 0.1,
            "h": 0.02185185185185185
          },
          "fillColor": "000000",
          "strokeColor": "000000"
        },
        {
          "type": "shape",
          "geomPreset": "rect",
          "position": {
            "x": 0.29201492782152233,
            "y": 0.7111258384368621,
            "w": 0.11119791666666666,
            "h": 0.055724117818606006
          },
          "text": "シーズー一人で仕事をすることを好み専門的な仕事に長けたタイプ",
          "fontSize": 8
        },
        {
          "type": "shape",
          "geomPreset": "rect",
          "position": {
            "x": 0.06875,
            "y": 0.5528442694663167,
            "w": 0.21875,
            "h": 0.03141498979294255
          },
          "text": "協定         行動         協力",
          "fontSize": 8
        },
        {
          "type": "shape",
          "geomPreset": "rect",
          "position": {
            "x": 0.0625,
            "y": 0.665350247885681,
            "w": 0.21875,
            "h": 0.03141498979294255
          },
          "text": "協定         行動         結果志向",
          "fontSize": 8
        },
        {
          "type": "shape",
          "geomPreset": "rect",
          "position": {
            "x": 0.06875,
            "y": 0.7789056576261301,
            "w": 0.21875,
            "h": 0.03141498979294255
          },
          "text": "協定          連結         支持",
          "fontSize": 8
        },
        {
          "type": "shape",
          "geomPreset": "rect",
          "position": {
            "x": 0.26875,
            "y": 0.5542624671916011,
            "w": 0.21875,
            "h": 0.03141498979294255
          },
          "text": "支持         安定性         協力",
          "fontSize": 8
        },
        {
          "type": "shape",
          "geomPreset": "rect",
          "position": {
            "x": 0.25625,
            "y": 0.665350247885681,
            "w": 0.21875,
            "h": 0.03141498979294255
          },
          "text": "協力         支持         協定",
          "fontSize": 8
        },
        {
          "type": "shape",
          "geomPreset": "rect",
          "position": {
            "x": 0.2741249179790026,
            "y": 0.7796628754738991,
            "w": 0.21875,
            "h": 0.03141498979294255
          },
          "text": "安定性        支持          正確性",
          "fontSize": 8
        },
        {
          "type": "pic",
          "geomPreset": "rect",
          "position": {
            "x": 0.22349991797900262,
            "y": 0.4679997083697871,
            "w": 0.05849991797900263,
            "h": 0.09288874307378245
          }
        },
        {
          "type": "pic",
          "geomPreset": "rect",
          "position": {
            "x": 0.22349991797900262,
            "y": 0.600888597258676,
            "w": 0.05849991797900263,
            "h": 0.09288874307378245
          }
        },
        {
          "type": "pic",
          "geomPreset": "rect",
          "position": {
            "x": 0.22349991797900262,
            "y": 0.7142219305920093,
            "w": 0.05849991797900263,
            "h": 0.09288874307378245
          }
        },
        {
          "type": "pic",
          "geomPreset": "rect",
          "position": {
            "x": 0.029499917979002626,
            "y": 0.600888597258676,
            "w": 0.05849991797900263,
            "h": 0.09288874307378245
          }
        },
        {
          "type": "pic",
          "geomPreset": "rect",
          "position": {
            "x": 0.029499917979002626,
            "y": 0.4679997083697871,
            "w": 0.05849991797900263,
            "h": 0.09288874307378245
          }
        },
        {
          "type": "pic",
          "geomPreset": "rect",
          "position": {
            "x": 0.029499917979002626,
            "y": 0.7142219305920093,
            "w": 0.05849991797900263,
            "h": 0.09288874307378245
          }
        }
      ]
    },
    {
      "slideNumber": 8,
      "shapes": [
        {
          "type": "shape",
          "position": {
            "x": 0.025749917979002626,
            "y": 0.6235552639253427,
            "w": 0.18927083333333333,
            "h": 0.002685185185185185
          },
          "fillColor": "000000",
          "strokeColor": "000000"
        },
        {
          "type": "shape",
          "position": {
            "x": 0.025749917979002626,
            "y": 0.6542219305920093,
            "w": 0.18927083333333333,
            "h": 0.002685185185185185
          },
          "fillColor": "000000",
          "strokeColor": "000000"
        },
        {
          "type": "shape",
          "position": {
            "x": 0.22274991797900262,
            "y": 0.6235552639253427,
            "w": 0.18901041666666665,
            "h": 0.002685185185185185
          },
          "fillColor": "000000",
          "strokeColor": "000000"
        },
        {
          "type": "shape",
          "position": {
            "x": 0.22274991797900262,
            "y": 0.6542219305920093,
            "w": 0.18901041666666665,
            "h": 0.002685185185185185
          },
          "fillColor": "000000",
          "strokeColor": "000000"
        },
        {
          "type": "shape",
          "position": {
            "x": 0.025749917979002626,
            "y": 0.6542219305920093,
            "w": 0.18927083333333333,
            "h": 0.002685185185185185
          },
          "fillColor": "000000",
          "strokeColor": "000000"
        },
        {
          "type": "shape",
          "position": {
            "x": 0.22274991797900262,
            "y": 0.6542219305920093,
            "w": 0.18901041666666665,
            "h": 0.002685185185185185
          },
          "fillColor": "000000",
          "strokeColor": "000000"
        },
        {
          "type": "shape",
          "position": {
            "x": 0.025749917979002626,
            "y": 0.7324441528142316,
            "w": 0.09276041666666666,
            "h": 0.002685185185185185
          },
          "fillColor": "000000",
          "strokeColor": "000000"
        },
        {
          "type": "shape",
          "position": {
            "x": 0.025749917979002626,
            "y": 0.7631108194808982,
            "w": 0.09276041666666666,
            "h": 0.002685185185185185
          },
          "fillColor": "000000",
          "strokeColor": "000000"
        },
        {
          "type": "shape",
          "position": {
            "x": 0.12624991797900262,
            "y": 0.7324441528142316,
            "w": 0.08875,
            "h": 0.002685185185185185
          },
          "fillColor": "000000",
          "strokeColor": "000000"
        },
        {
          "type": "shape",
          "position": {
            "x": 0.12624991797900262,
            "y": 0.7631108194808982,
            "w": 0.08875,
            "h": 0.002685185185185185
          },
          "fillColor": "000000",
          "strokeColor": "000000"
        },
        {
          "type": "shape",
          "position": {
            "x": 0.22274991797900262,
            "y": 0.7324441528142316,
            "w": 0.08875,
            "h": 0.002685185185185185
          },
          "fillColor": "000000",
          "strokeColor": "000000"
        },
        {
          "type": "shape",
          "position": {
            "x": 0.22274991797900262,
            "y": 0.7631108194808982,
            "w": 0.08875,
            "h": 0.002685185185185185
          },
          "fillColor": "000000",
          "strokeColor": "000000"
        },
        {
          "type": "shape",
          "position": {
            "x": 0.31924991797900265,
            "y": 0.7324441528142316,
            "w": 0.0925,
            "h": 0.002685185185185185
          },
          "fillColor": "000000",
          "strokeColor": "000000"
        },
        {
          "type": "shape",
          "position": {
            "x": 0.31924991797900265,
            "y": 0.7631108194808982,
            "w": 0.0925,
            "h": 0.002685185185185185
          },
          "fillColor": "000000",
          "strokeColor": "000000"
        },
        {
          "type": "shape",
          "position": {
            "x": 0.025749917979002626,
            "y": 0.7631108194808982,
            "w": 0.09276041666666666,
            "h": 0.002685185185185185
          },
          "fillColor": "000000",
          "strokeColor": "000000"
        },
        {
          "type": "shape",
          "position": {
            "x": 0.12624991797900262,
            "y": 0.7631108194808982,
            "w": 0.08875,
            "h": 0.002685185185185185
          },
          "fillColor": "000000",
          "strokeColor": "000000"
        },
        {
          "type": "shape",
          "position": {
            "x": 0.22274991797900262,
            "y": 0.7631108194808982,
            "w": 0.08875,
            "h": 0.002685185185185185
          },
          "fillColor": "000000",
          "strokeColor": "000000"
        },
        {
          "type": "shape",
          "position": {
            "x": 0.31924991797900265,
            "y": 0.7631108194808982,
            "w": 0.0925,
            "h": 0.002685185185185185
          },
          "fillColor": "000000",
          "strokeColor": "000000"
        },
        {
          "type": "shape",
          "position": {
            "x": 0.025749917979002626,
            "y": 0.9155552639253427,
            "w": 0.09276041666666666,
            "h": 0.002685185185185185
          },
          "fillColor": "000000",
          "strokeColor": "000000"
        },
        {
          "type": "shape",
          "position": {
            "x": 0.12624991797900262,
            "y": 0.9155552639253427,
            "w": 0.08875,
            "h": 0.002685185185185185
          },
          "fillColor": "000000",
          "strokeColor": "000000"
        },
        {
          "type": "shape",
          "position": {
            "x": 0.025749917979002626,
            "y": 0.9155552639253427,
            "w": 0.09276041666666666,
            "h": 0.002685185185185185
          },
          "fillColor": "000000",
          "strokeColor": "000000"
        },
        {
          "type": "shape",
          "position": {
            "x": 0.025749917979002626,
            "y": 0.9462219305920093,
            "w": 0.09276041666666666,
            "h": 0.002685185185185185
          },
          "fillColor": "000000",
          "strokeColor": "000000"
        },
        {
          "type": "shape",
          "position": {
            "x": 0.12624991797900262,
            "y": 0.9155552639253427,
            "w": 0.08875,
            "h": 0.002685185185185185
          },
          "fillColor": "000000",
          "strokeColor": "000000"
        },
        {
          "type": "shape",
          "position": {
            "x": 0.12624991797900262,
            "y": 0.9462219305920093,
            "w": 0.08875,
            "h": 0.002685185185185185
          },
          "fillColor": "000000",
          "strokeColor": "000000"
        },
        {
          "type": "shape",
          "position": {
            "x": 0.025749917979002626,
            "y": 0.9462219305920093,
            "w": 0.09276041666666666,
            "h": 0.002685185185185185
          },
          "fillColor": "000000",
          "strokeColor": "000000"
        },
        {
          "type": "shape",
          "position": {
            "x": 0.12624991797900262,
            "y": 0.9462219305920093,
            "w": 0.08875,
            "h": 0.002685185185185185
          },
          "fillColor": "000000",
          "strokeColor": "000000"
        },
        {
          "type": "shape",
          "geomPreset": "rect",
          "position": {
            "x": 0.39945833333333336,
            "y": 0.03014814814814815,
            "w": 0.013333333333333334,
            "h": 0.023981481481481482
          },
          "text": "07",
          "fontSize": 9
        },
        {
          "type": "shape",
          "geomPreset": "rect",
          "position": {
            "x": 0.03216535433070866,
            "y": 0.11592592592592593,
            "w": 0.04895833333333333,
            "h": 0.028796296296296296
          },
          "text": "진단결과",
          "fillColor": "FFFFFF",
          "strokeColor": "FFFFFF",
          "textColor": "FFFFFF",
          "fontSize": 11
        },
        {
          "type": "shape",
          "geomPreset": "rect",
          "position": {
            "x": 0.02446998031496063,
            "y": 0.2506901428988043,
            "w": 0.3942800196850394,
            "h": 0.2954499854184894
          },
          "text": "思考型タイプ (Organizer)卓越した知的能力を土台に現象を解釈し、自分だけの解決策を作り出します。彼らの戦略は驚くほど精巧です。目標遂行、組織構成そして課題自体に対する体系的な思考能力は、時には他人に共感を得られず組織力を害することもある傾向を見せます。サプサル犬(OD)サプサル犬は分析能力が非常に優れており、挑戦を楽しみます。事実的な資料を土台に結論を引き出し行動します。しかし時には直観的な情報と客観的な資料を結合した方式で仕事を効果的に処理することもあります。サプサル犬は多様な質問と何度もの検討を進めた後に新しいアイデアを受け入れ、本人がよく知らない仕事であれば非難を避けるために徹底的に準備します。一方で他の人々から断固として、冷たく、厳格で、頑固だという評価を受けることがあります。実際にサプサル犬は無愛想で批判的であり、時には他の人の欲求や感情を無視することもあります。また合理的な意思決定のためであれば、望む結果を得るためであれば本人の欲求と感情さえも分離することもあります。",
          "fillColor": "8387B6",
          "textColor": "8387B6",
          "fontSize": 9
        },
        {
          "type": "shape",
          "geomPreset": "rect",
          "position": {
            "x": 0.02446998031496063,
            "y": 0.5901480023330417,
            "w": 0.05427985564304462,
            "h": 0.0222522601341499
          },
          "text": "態度/性格",
          "fillColor": "8387B6",
          "strokeColor": "8387B6",
          "textColor": "8387B6",
          "fontSize": 9
        },
        {
          "type": "shape",
          "geomPreset": "rect",
          "position": {
            "x": 0.02470825131233596,
            "y": 0.659481335666375,
            "w": 0.11279174868766405,
            "h": 0.01963429571303587
          },
          "text": "厳格な基準、断固たる接近",
          "fontSize": 8
        },
        {
          "type": "shape",
          "geomPreset": "rect",
          "position": {
            "x": 0.22170816929133857,
            "y": 0.659481335666375,
            "w": 0.10329174868766404,
            "h": 0.01963429571303587
          },
          "text": "批判的態度、無愛想さ",
          "fontSize": 8
        },
        {
          "type": "shape",
          "geomPreset": "rect",
          "position": {
            "x": 0.024708169291338584,
            "y": 0.8048148148148148,
            "w": 0.037791748687664044,
            "h": 0.01963429571303587
          },
          "text": "正確性",
          "fontSize": 8
        },
        {
          "type": "shape",
          "geomPreset": "rect",
          "position": {
            "x": 0.12520825131233596,
            "y": 0.7724591717701954,
            "w": 0.08973958333333333,
            "h": 0.07984631087780694
          },
          "text": "曖昧な状況、抽象的で観念的な考えを説明しなければならない状況",
          "fontSize": 8
        },
        {
          "type": "shape",
          "geomPreset": "rect",
          "position": {
            "x": 0.22170825131233596,
            "y": 0.7704101778944299,
            "w": 0.08880208333333334,
            "h": 0.09162685914260718
          },
          "text": "用語、イシュー、手続き、状況などの意味を明確に定義、情報収集、自身及び他の人の業務遂行を評価し分析",
          "fontSize": 8
        },
        {
          "type": "shape",
          "geomPreset": "rect",
          "position": {
            "x": 0.3182083333333333,
            "y": 0.8048148148148148,
            "w": 0.08567708333333333,
            "h": 0.01963429571303587
          },
          "text": "論理的に考える能力",
          "fontSize": 8
        },
        {
          "type": "shape",
          "geomPreset": "rect",
          "position": {
            "x": 0.22170825131233596,
            "y": 0.9275702828813065,
            "w": 0.08458333333333333,
            "h": 0.04562642169728784
          },
          "text": "融通性を持つ他の人を受け入れる",
          "fontSize": 8
        },
        {
          "type": "shape",
          "geomPreset": "rect",
          "position": {
            "x": 0.02470825131233596,
            "y": 0.9634814814814815,
            "w": 0.07529174868766404,
            "h": 0.01739034703995334
          },
          "text": "心配が多くなる",
          "fontSize": 7
        },
        {
          "type": "shape",
          "geomPreset": "rect",
          "position": {
            "x": 0.12520825131233596,
            "y": 0.9435702828813065,
            "w": 0.08973958333333333,
            "h": 0.05044167395742199
          },
          "text": "事実に基づいた資料、論理的な主張",
          "fillColor": "333333",
          "strokeColor": "333333",
          "textColor": "333333",
          "fontSize": 7.5
        },
        {
          "type": "shape",
          "geomPreset": "rect",
          "position": {
            "x": 0.02420242782152231,
            "y": 0.15325925925925926,
            "w": 0.3445475721784777,
            "h": 0.08843875765529309
          },
          "text": "OOさんのDOGS タイプを見てみましょう",
          "placeholderType": "title"
        },
        {
          "type": "shape",
          "geomPreset": "flowChartTerminator",
          "position": {
            "x": 0.02420242782152231,
            "y": 0.07992767570720327,
            "w": 0.08675,
            "h": 0.04273724117818606
          },
          "text": "診断結果",
          "fontSize": 12
        },
        {
          "type": "shape",
          "geomPreset": "rect",
          "position": {
            "x": 0.02446998031496063,
            "y": 0.8852592592592593,
            "w": 0.08178001968503937,
            "h": 0.0222522601341499
          },
          "text": "同僚に対する時",
          "fillColor": "8387B6",
          "strokeColor": "8387B6",
          "textColor": "8387B6",
          "fontSize": 9
        },
        {
          "type": "shape",
          "geomPreset": "rect",
          "position": {
            "x": 0.22146998031496062,
            "y": 0.8857035578885972,
            "w": 0.12228001968503938,
            "h": 0.0222522601341499
          },
          "text": "こうすればもっと良いです",
          "fillColor": "8387B6",
          "strokeColor": "8387B6",
          "textColor": "8387B6",
          "fontSize": 9
        },
        {
          "type": "shape",
          "geomPreset": "rect",
          "position": {
            "x": 0.02451492782152231,
            "y": 0.6287037037037037,
            "w": 0.016666666666666666,
            "h": 0.01963429571303587
          },
          "text": "強み",
          "fontSize": 8
        },
        {
          "type": "shape",
          "geomPreset": "rect",
          "position": {
            "x": 0.22151492782152232,
            "y": 0.6287037037037037,
            "w": 0.016666666666666666,
            "h": 0.01963429571303587
          },
          "text": "弱み",
          "fontSize": 8
        },
        {
          "type": "shape",
          "geomPreset": "rect",
          "position": {
            "x": 0.02451492782152231,
            "y": 0.7398148148148148,
            "w": 0.016666666666666666,
            "h": 0.01963429571303587
          },
          "text": "好み",
          "fontSize": 8
        },
        {
          "type": "shape",
          "geomPreset": "rect",
          "position": {
            "x": 0.12501492782152232,
            "y": 0.7398148148148148,
            "w": 0.016666666666666666,
            "h": 0.01963429571303587
          },
          "text": "忌避",
          "fontSize": 8
        },
        {
          "type": "shape",
          "geomPreset": "rect",
          "position": {
            "x": 0.22151492782152232,
            "y": 0.7398148148148148,
            "w": 0.04723507217847769,
            "h": 0.01963429571303587
          },
          "text": "業務する時",
          "fontSize": 8
        },
        {
          "type": "shape",
          "geomPreset": "rect",
          "position": {
            "x": 0.3180149278215223,
            "y": 0.7398148148148148,
            "w": 0.04932291666666667,
            "h": 0.01963429571303587
          },
          "text": "圧力がある時",
          "fontSize": 8
        },
        {
          "type": "shape",
          "geomPreset": "rect",
          "position": {
            "x": 0.025,
            "y": 0.9224139690871974,
            "w": 0.053171259842519684,
            "h": 0.01963429571303587
          },
          "text": "判断する時",
          "fontSize": 8
        },
        {
          "type": "shape",
          "geomPreset": "rect",
          "position": {
            "x": 0.12501492782152232,
            "y": 0.9224139690871974,
            "w": 0.06873507217847769,
            "h": 0.01963429571303587
          },
          "text": "影響を与える時",
          "fontSize": 8
        },
        {
          "type": "shape",
          "geomPreset": "rect",
          "position": {
            "x": 0.02446998031496063,
            "y": 0.7049628171478565,
            "w": 0.06928001968503937,
            "h": 0.0222522601341499
          },
          "text": "仕事をする時",
          "fillColor": "8387B6",
          "strokeColor": "8387B6",
          "textColor": "8387B6",
          "fontSize": 9
        },
        {
          "type": "shape",
          "geomPreset": "rect",
          "position": {
            "x": 0,
            "y": 0,
            "w": 1,
            "h": 1
          },
          "text": "判断する時 事実に基づいた資料、論理的な主張影響を与える時(記載なし)こうすればもっと良いです融通性を持つ他の人を受け入れる",
          "fontSize": 9
        },
        {
          "type": "pic",
          "geomPreset": "rect",
          "position": {
            "x": 0.025749917979002626,
            "y": 0.03288888888888889,
            "w": 0.05299991797900262,
            "h": 0.016444298629337998
          }
        }
      ]
    },
    {
      "slideNumber": 9,
      "shapes": [
        {
          "type": "shape",
          "geomPreset": "rect",
          "position": {
            "x": 0.39945833333333336,
            "y": 0.02970355788859726,
            "w": 0.013333333333333334,
            "h": 0.023981481481481482
          },
          "text": "08",
          "fontSize": 9
        },
        {
          "type": "shape",
          "geomPreset": "rect",
          "position": {
            "x": 0.025749917979002626,
            "y": 0.3102219305920093,
            "w": 0.06625,
            "h": 0.0560981335666375
          },
          "text": "ロットワイラー(DO)",
          "fillColor": "000000",
          "strokeColor": "8387B6",
          "textColor": "8387B6",
          "fontSize": 9
        },
        {
          "type": "shape",
          "geomPreset": "rect",
          "position": {
            "x": 0.02443290682414698,
            "y": 0.09237037037037037,
            "w": 0.3891145833333333,
            "h": 0.18436643336249636
          },
          "text": "強化・補完タイプ強み強化タイプロットワイラーはサプサル犬の厳格さに高い業務基準を加えて完璧度を高めます。また主導的な性向を持っているため、サプサル犬が結果を出そうとする方向に力を加えてより速く結果を見られるようにします。",
          "fillColor": "8387B6",
          "strokeColor": "8387B6",
          "textColor": "8387B6",
          "fontSize": 10.5
        },
        {
          "type": "shape",
          "geomPreset": "rect",
          "position": {
            "x": 0.025749917979002626,
            "y": 0.49155526392534266,
            "w": 0.06625,
            "h": 0.050488334791484395
          },
          "text": "ボーダーコリー(OO)",
          "fillColor": "000000",
          "textColor": "8387B6",
          "fontSize": 9
        },
        {
          "type": "shape",
          "geomPreset": "rect",
          "position": {
            "x": 0.09870833333333333,
            "y": 0.38179250510352875,
            "w": 0.31427083333333333,
            "h": 0.07954709827938175
          },
          "text": "ボーダーコリーはサプサル犬よりさらに分析的であるため、サプサル犬が見逃す可能性がある部分を類似した観点と価値観の中で気遣う役割をします。このおかげでサプサル犬はさらに高い水準の成果物を導出することができます。",
          "fontSize": 8
        },
        {
          "type": "shape",
          "geomPreset": "rect",
          "position": {
            "x": 0.025749917979002626,
            "y": 0.7586663750364537,
            "w": 0.06625,
            "h": 0.07068358121901429
          },
          "text": "セントバーナード(GS)",
          "fillColor": "000000",
          "strokeColor": "8387B6",
          "textColor": "8387B6",
          "fontSize": 9
        },
        {
          "type": "shape",
          "geomPreset": "rect",
          "position": {
            "x": 0.02446998031496063,
            "y": 0.607037037037037,
            "w": 0.3890625,
            "h": 0.14502303878681833
          },
          "text": "弱み補完タイプ概ね厳格で時には他人の欲求と感情を無視することもあるサプサル犬は、協業において障害物になることもあります。関係志向的な価値を持つセントバーナードと共にすれば、サプサル犬の行動で傷つくチームメンバーがいないように世話をしながら協業していくことができます。",
          "fillColor": "8387B6",
          "textColor": "8387B6",
          "fontSize": 9
        },
        {
          "type": "shape",
          "geomPreset": "rect",
          "position": {
            "x": 0.025749917979002626,
            "y": 0.9399997083697871,
            "w": 0.06625,
            "h": 0.050488334791484395
          },
          "text": "ウェルシュコーギー(SG)",
          "fillColor": "000000",
          "strokeColor": "8387B6",
          "textColor": "8387B6",
          "fontSize": 9
        },
        {
          "type": "shape",
          "geomPreset": "rect",
          "position": {
            "x": 0.09870833333333333,
            "y": 0.8302369495479732,
            "w": 0.31307291666666665,
            "h": 0.07954709827938175
          },
          "text": "ウェルシュコーギーは成果物を出すにおいてすべてのチームメンバーが共にできるようにチームメンバーをよく気遣う役割をします。ウェルシュコーギー特有の活発さと魅力でチームメンバーを団結させサプサル犬を助けて成果物を導出します。",
          "fontSize": 8
        },
        {
          "type": "pic",
          "geomPreset": "rect",
          "position": {
            "x": 0.025749917979002626,
            "y": 0.2057774861475649,
            "w": 0.06624991797900262,
            "h": 0.104444298629338
          }
        },
        {
          "type": "pic",
          "geomPreset": "rect",
          "position": {
            "x": 0.025749917979002626,
            "y": 0.3871108194808982,
            "w": 0.06624991797900262,
            "h": 0.104444298629338
          }
        },
        {
          "type": "pic",
          "geomPreset": "rect",
          "position": {
            "x": 0.025749917979002626,
            "y": 0.6542219305920093,
            "w": 0.06624991797900262,
            "h": 0.104444298629338
          }
        },
        {
          "type": "pic",
          "geomPreset": "rect",
          "position": {
            "x": 0.025749917979002626,
            "y": 0.8355552639253426,
            "w": 0.06624991797900262,
            "h": 0.104444298629338
          }
        }
      ]
    },
    {
      "slideNumber": 10,
      "shapes": [
        {
          "type": "shape",
          "geomPreset": "rect",
          "position": {
            "x": 0.39945833333333336,
            "y": 0.029259113444152815,
            "w": 0.013333333333333334,
            "h": 0.023981481481481482
          },
          "text": "06",
          "fontSize": 9
        },
        {
          "type": "shape",
          "geomPreset": "rect",
          "position": {
            "x": 0.03216535433070866,
            "y": 0.11503703703703703,
            "w": 0.06,
            "h": 0.028796296296296296
          },
          "text": "리더십유형",
          "fillColor": "FFFFFF",
          "strokeColor": "FFFFFF",
          "textColor": "FFFFFF",
          "fontSize": 11
        },
        {
          "type": "shape",
          "geomPreset": "rect",
          "position": {
            "x": 0.02420242782152231,
            "y": 0.15325925925925926,
            "w": 0.2820475721784777,
            "h": 0.08770005832604258
          },
          "text": "DOGS リーダーシップタイプは何ですか?",
          "placeholderType": "title"
        },
        {
          "type": "shape",
          "geomPreset": "rect",
          "position": {
            "x": 0.02470825131233596,
            "y": 0.2511259842519685,
            "w": 0.38869791666666664,
            "h": 0.10437051618547681
          },
          "text": "DOGS 業務タイプ診断モデル 管理型(D)、思考型(O)、案内型(G)、支援型(S)が実務者からリーダーになると、それぞれ指示型、活力型、包容型、慎重型のいずれかのリーダーシップスタイルを持ちます。また、業務性向が重なる場合、同一のリーダーシップ特徴を示します。管理型と案内型性向を持つDG(ビーグル)とGD(ビション・フリーゼ)は開拓型リーダーシップに区分される原理です。",
          "fontSize": 8
        },
        {
          "type": "shape",
          "geomPreset": "flowChartTerminator",
          "position": {
            "x": 0.02420242782152231,
            "y": 0.07948308544765238,
            "w": 0.0882975721784777,
            "h": 0.04273724117818606
          },
          "text": "リーダーシップタイプ",
          "fontSize": 9
        },
        {
          "type": "shape",
          "geomPreset": "flowChartTerminator",
          "position": {
            "x": 0.094248687664042,
            "y": 0.46574074074074073,
            "w": 0.03125,
            "h": 0.022222222222222223
          },
          "text": "DG",
          "fontSize": 9
        },
        {
          "type": "shape",
          "geomPreset": "flowChartTerminator",
          "position": {
            "x": 0.094248687664042,
            "y": 0.4891093613298338,
            "w": 0.03125,
            "h": 0.022222222222222223
          },
          "text": "GD",
          "fontSize": 9
        },
        {
          "type": "shape",
          "geomPreset": "flowChartTerminator",
          "position": {
            "x": 0.09375,
            "y": 0.5320855934674832,
            "w": 0.0375,
            "h": 0.022222222222222223
          },
          "text": "CG",
          "fontSize": 9
        },
        {
          "type": "shape",
          "geomPreset": "flowChartTerminator",
          "position": {
            "x": 0.096875,
            "y": 0.5830705745115194,
            "w": 0.03125,
            "h": 0.022222222222222223
          },
          "text": "GS",
          "fontSize": 9
        },
        {
          "type": "shape",
          "geomPreset": "flowChartTerminator",
          "position": {
            "x": 0.096875,
            "y": 0.6064982502187226,
            "w": 0.03125,
            "h": 0.022222222222222223
          },
          "text": "SG",
          "fontSize": 9
        },
        {
          "type": "shape",
          "geomPreset": "flowChartTerminator",
          "position": {
            "x": 0.096875,
            "y": 0.6487257217847769,
            "w": 0.03125,
            "h": 0.022222222222222223
          },
          "text": "SS",
          "fontSize": 9
        },
        {
          "type": "shape",
          "geomPreset": "flowChartTerminator",
          "position": {
            "x": 0.096875,
            "y": 0.6961614173228347,
            "w": 0.03125,
            "h": 0.022222222222222223
          },
          "text": "SO",
          "fontSize": 9
        },
        {
          "type": "shape",
          "geomPreset": "flowChartTerminator",
          "position": {
            "x": 0.096875,
            "y": 0.7213748906386702,
            "w": 0.03125,
            "h": 0.022222222222222223
          },
          "text": "OS",
          "fontSize": 9
        },
        {
          "type": "shape",
          "geomPreset": "flowChartTerminator",
          "position": {
            "x": 0.09375,
            "y": 0.7622594050743657,
            "w": 0.0375,
            "h": 0.022222222222222223
          },
          "text": "OO",
          "fontSize": 9
        },
        {
          "type": "shape",
          "geomPreset": "flowChartTerminator",
          "position": {
            "x": 0.0949219160104987,
            "y": 0.8126863517060368,
            "w": 0.0375,
            "h": 0.022222222222222223
          },
          "text": "OD",
          "fontSize": 9
        },
        {
          "type": "shape",
          "geomPreset": "flowChartTerminator",
          "position": {
            "x": 0.09414066601049868,
            "y": 0.8373199183435404,
            "w": 0.0375,
            "h": 0.022222222222222223
          },
          "text": "DO",
          "fontSize": 9
        },
        {
          "type": "shape",
          "geomPreset": "flowChartTerminator",
          "position": {
            "x": 0.0949219160104987,
            "y": 0.8833149606299212,
            "w": 0.0375,
            "h": 0.022222222222222223
          },
          "text": "DD",
          "fontSize": 9
        },
        {
          "type": "pic",
          "geomPreset": "rect",
          "position": {
            "x": 0.025749917979002626,
            "y": 0.032,
            "w": 0.05299991797900262,
            "h": 0.016444298629337998
          }
        },
        {
          "type": "table",
          "position": {
            "x": 0,
            "y": 0,
            "w": 1,
            "h": 1
          },
          "text": "タイプ種類タイプ特徴開拓型Pioneering                  ビーグル                   ビション・フリーゼ挑戦的な目標を立てて同僚たちと共に達成していくタイプ活力型Energizer                  プードル堅固なネットワークを土台に協力して仕事を推進するタイプ公正型Affirming                 セントバーナード                 ウェルシュコーギー温かく真実味があり他人が容易に近づくタイプ包容型Inclusiveゴールデンレトリバー  協業し受容する環境を造成するタイプ謙遜型Humble                 シーズー珍島犬慎重で公正であり信頼されようとする目標を持つタイプ慎重型Deliberateボーダーコリー 客観的で明確にコミュニケーションして いくタイプ断固型Resolute                  サプサル犬                  ロットワイラー合理的で独立的であり他人に高い基準を要求するタイプ指示型Commandingドーベルマン 成果を出すことに積極的で競争心が強い タイプ",
          "fillColor": "FFFFFF",
          "strokeColor": "FFFFFF",
          "textColor": "FFFFFF",
          "fontSize": 9
        }
      ]
    },
    {
      "slideNumber": 11,
      "shapes": [
        {
          "type": "shape",
          "geomPreset": "rect",
          "position": {
            "x": 0.39945833333333336,
            "y": 0.02881466899970837,
            "w": 0.013333333333333334,
            "h": 0.023981481481481482
          },
          "text": "10",
          "fontSize": 9
        },
        {
          "type": "shape",
          "geomPreset": "rect",
          "position": {
            "x": 0.03216535433070866,
            "y": 0.11459244677748615,
            "w": 0.08473950131233596,
            "h": 0.02702055993000875
          },
          "text": "리더십진단결과",
          "fillColor": "FFFFFF",
          "strokeColor": "FFFFFF",
          "textColor": "FFFFFF",
          "fontSize": 11
        },
        {
          "type": "shape",
          "geomPreset": "rect",
          "position": {
            "x": 0.02446998031496063,
            "y": 0.26597039953339163,
            "w": 0.06303001968503937,
            "h": 0.05319962088072324
          },
          "text": "断固型リーダー(Resolute)",
          "fillColor": "333333",
          "strokeColor": "333333",
          "textColor": "333333",
          "fontSize": 9
        },
        {
          "type": "shape",
          "geomPreset": "rect",
          "position": {
            "x": 0.12895833333333334,
            "y": 0.2644591717701954,
            "w": 0.2841666666666667,
            "h": 0.10957830271216099
          },
          "text": "厳格で粘り強いです。生まれつきの懐疑論者であり、弱点と無能さを軽視する傾向があります。正しい方式で、本人が望む方式通りに仕事が進むことを見たいため、「すべきだ」という言葉をよく使います。断固型リーダーは自らを非常に有能で、厳格であり、合理的で、独立的であり、挑戦する人として評価するでしょう。本人と他人に高い基準を要求し、非効率的な部分や問題を見た時、指摘することを恐れません。",
          "fontSize": 8
        },
        {
          "type": "shape",
          "geomPreset": "rect",
          "position": {
            "x": 0.12895833333333334,
            "y": 0.4225925925925926,
            "w": 0.16479166666666667,
            "h": 0.01963429571303587
          },
          "text": "独立性、個人的達成、効率的な成果物",
          "fontSize": 8
        },
        {
          "type": "shape",
          "geomPreset": "rect",
          "position": {
            "x": 0.12895833333333334,
            "y": 0.46712583843686206,
            "w": 0.28979166666666667,
            "h": 0.07367556138815981
          },
          "text": "計画内に隠れた弱点を発見し障害物を克服する力を持つ優れた問題解決者です。目標を達成するのに十分な競争心を持っています。人々に責任を負わせることができ、直観的なフィードバックを与えることを恐れません。",
          "fontSize": 8
        },
        {
          "type": "shape",
          "geomPreset": "rect",
          "position": {
            "x": 0.02446998031496063,
            "y": 0.6234813356663751,
            "w": 0.08895833333333333,
            "h": 0.04244750656167979
          },
          "text": "こうすればもっと良いです",
          "fontSize": 9
        },
        {
          "type": "shape",
          "geomPreset": "rect",
          "position": {
            "x": 0.12895833333333334,
            "y": 0.6169036162146398,
            "w": 0.12829174868766405,
            "h": 0.0377726742490522
          },
          "text": "多様性を認める正しい・間違いから抜け出す",
          "fontSize": 8
        },
        {
          "type": "shape",
          "geomPreset": "rect",
          "position": {
            "x": 0.02420242782152231,
            "y": 0.15325925925925926,
            "w": 0.3820475721784777,
            "h": 0.08770005832604258
          },
          "text": "OOさんのリーダーシップ特徴を確認してみましょう",
          "placeholderType": "title"
        },
        {
          "type": "shape",
          "position": {
            "x": 0.025749917979002626,
            "y": 0.10888874307378245,
            "w": 0.1305000820209974,
            "h": 0.038703703703703705
          },
          "fillColor": "000000",
          "strokeColor": "000000"
        },
        {
          "type": "shape",
          "geomPreset": "rect",
          "position": {
            "x": 0.03216535433070866,
            "y": 0.11459244677748615,
            "w": 0.14908464566929133,
            "h": 0.02702055993000875
          },
          "text": "リーダーシップ診断結果",
          "fontSize": 11
        },
        {
          "type": "shape",
          "geomPreset": "rect",
          "position": {
            "x": 0.02446998031496063,
            "y": 0.41997462817147857,
            "w": 0.05427985564304462,
            "h": 0.0222522601341499
          },
          "text": "チーム目標",
          "fontSize": 9
        },
        {
          "type": "shape",
          "geomPreset": "rect",
          "position": {
            "x": 0.02446998031496063,
            "y": 0.46708078156897054,
            "w": 0.01994783464566929,
            "h": 0.0222522601341499
          },
          "text": "強み",
          "fontSize": 9
        },
        {
          "type": "pic",
          "geomPreset": "rect",
          "position": {
            "x": 0.025749917979002626,
            "y": 0.03155555555555556,
            "w": 0.05299991797900262,
            "h": 0.016444298629337998
          }
        },
        {
          "type": "pic",
          "geomPreset": "rect",
          "position": {
            "x": 0,
            "y": 1.0968884514435695,
            "w": 0.4374999179790026,
            "h": 0.004888743073782444
          }
        }
      ]
    },
    {
      "slideNumber": 12,
      "shapes": [
        {
          "type": "shape",
          "geomPreset": "rect",
          "position": {
            "x": 0.3579583333333333,
            "y": 0.02837037037037037,
            "w": 0.054739583333333335,
            "h": 0.023981481481481482
          },
          "text": "DOGSTEST",
          "fontSize": 9
        },
        {
          "type": "shape",
          "geomPreset": "rect",
          "position": {
            "x": 0.023666830708661418,
            "y": 0.47459244677748613,
            "w": 0.009843667979002624,
            "h": 0.14203703703703704
          },
          "text": "www.testdogs.co.kr",
          "fontSize": 7.5
        },
        {
          "type": "shape",
          "geomPreset": "rect",
          "position": {
            "x": 0.40166683070866144,
            "y": 0.47459244677748613,
            "w": 0.009843667979002624,
            "h": 0.15601851851851853
          },
          "text": "www.underdogs.co.kr",
          "fontSize": 7.5
        },
        {
          "type": "shape",
          "geomPreset": "rect",
          "position": {
            "x": 0.02446998031496063,
            "y": 1.0408146689997084,
            "w": 0.011041666666666667,
            "h": 0.023981481481481482
          },
          "text": "o",
          "fontSize": 9
        },
        {
          "type": "shape",
          "geomPreset": "rect",
          "position": {
            "x": 0.3737083333333333,
            "y": 1.0408146689997084,
            "w": 0.038802083333333334,
            "h": 0.023981481481481482
          },
          "text": "2025.11",
          "fontSize": 9
        },
        {
          "type": "shape",
          "geomPreset": "rect",
          "position": {
            "x": 0.04375,
            "y": 0.4910806357538641,
            "w": 0.34999991797900265,
            "h": 0.12304184893554972
          },
          "text": "それでは、○○さんのDOGS性格に基づいて、チームメンバーとコミュニケーションを始めましょう。"
        },
        {
          "type": "pic",
          "geomPreset": "rect",
          "position": {
            "x": 0,
            "y": 0,
            "w": 1,
            "h": 1
          }
        },
        {
          "type": "pic",
          "geomPreset": "rect",
          "position": {
            "x": 0.025749917979002626,
            "y": 0.031110965296004666,
            "w": 0.05299991797900262,
            "h": 0.016444298629337998
          }
        }
      ]
    }
  ],
  "extractedAt": "2026-05-30T06:56:53.610Z"
}